{
  "sequence_version": 1,
  "exercise": "red",
  "source": "synthetic_default",
  "profile": {
    "label": "red",
    "anchor": "mouth",
    "hand_shape": "index_point",
    "path": "mouth_brush_down",
    "hand_scale": 0.17
  },
  "frame_count_original": 30,
  "usable_frame_count": 30,
  "resampled_frame_count": 30,
  "handedness": "right",
  "frames": [
    {
      "handedness": "right",
      "hand_landmarks": [
        [
          0.4699999988079071,
          0.3499999940395355,
          0.0
        ],
        [
          0.47679999470710754,
          0.3482999801635742,
          0.0
        ],
        [
          0.48019999265670776,
          0.344899982213974,
          0.0
        ],
        [
          0.483599990606308,
          0.3414999842643738,
          0.0
        ],
        [
          0.4887000024318695,
          0.33980000019073486,
          0.0
        ],
        [
          0.47510001063346863,
          0.3330000042915344,
          0.0
        ],
        [
          0.47510001063346863,
          0.3125999867916107,
          0.0
        ],
        [
          0.47510001063346863,
          0.2888000011444092,
          0.0
        ],
        [
          0.47510001063346863,
          0.26159998774528503,
          0.0
        ],
        [
          0.4699999988079071,
          0.33640000224113464,
          0.0
        ],
        [
          0.4699999988079071,
          0.3296000063419342,
          0.0
        ],
        [
          0.4699999988079071,
          0.3244999945163727,
          0.0
        ],
        [
          0.4699999988079071,
          0.3227999806404114,
          0.0
        ],
        [
          0.4648999869823456,
          0.33640000224113464,
          0.0
        ],
        [
          0.4648999869823456,
          0.3312999904155731,
          0.0
        ],
        [
          0.4648999869823456,
          0.3278999924659729,
          0.0
        ],
        [
          0.4648999869823456,
          0.326200008392334,
          0.0
        ],
        [
          0.45980000495910645,
          0.33809998631477356,
          0.0
        ],
        [
          0.45980000495910645,
          0.3330000042915344,
          0.0
        ],
        [
          0.45980000495910645,
          0.3296000063419342,
          0.0
        ],
        [
          0.45980000495910645,
          0.3278999924659729,
          0.0
        ]
      ],
      "hand_center": [
        0.4704046845436096,
        0.3278190493583679,
        0.0
      ],
      "openness": 2.3032357692718506,
      "palm_size": 0.01612761616706848,
      "scale_hint": 0.24,
      "anchors": {
        "forehead": [
          0.5,
          0.23999999463558197,
          0.0
        ],
        "mouth": [
          0.5,
          0.3499999940395355,
          0.0
        ],
        "chin": [
          0.5,
          0.41999998688697815,
          0.0
        ],
        "left_shoulder": [
          0.3799999952316284,
          0.6200000047683716,
          0.0
        ],
        "right_shoulder": [
          0.6200000047683716,
          0.6200000047683716,
          0.0
        ],
        "shoulder_center": [
          0.5,
          0.6200000047683716,
          0.0
        ],
        "nose": [
          0.5,
          0.3100000023841858,
          0.0
        ],
        "scale_hint": 0.24
      }
    },
    {
      "handedness": "right",
      "hand_landmarks": [
        [
          0.47068965435028076,
          0.35413792729377747,
          0.0
        ],
        [
          0.4774896502494812,
          0.35243791341781616,
          0.0
        ],
        [
          0.4808896481990814,
          0.34903791546821594,
          0.0
        ],
        [
          0.48428964614868164,
          0.3456379175186157,
          0.0
        ],
        [
          0.48938965797424316,
          0.3439379334449768,
          0.0
        ],
        [
          0.4757896661758423,
          0.33713793754577637,
          0.0
        ],
        [
          0.4757896661758423,
          0.31673792004585266,
          0.0
        ],
        [
          0.4757896661758423,
          0.2929379343986511,
          0.0
        ],
        [
          0.4757896661758423,
          0.265737920999527,
          0.0
        ],
        [
          0.47068965435028076,
          0.3405379354953766,
          0.0
        ],
        [
          0.47068965435028076,
          0.33373793959617615,
          0.0
        ],
        [
          0.47068965435028076,
          0.3286379277706146,
          0.0
        ],
        [
          0.47068965435028076,
          0.3269379138946533,
          0.0
        ],
        [
          0.46558964252471924,
          0.3405379354953766,
          0.0
        ],
        [
          0.46558964252471924,
          0.33543792366981506,
          0.0
        ],
        [
          0.46558964252471924,
          0.33203792572021484,
          0.0
        ],
        [
          0.46558964252471924,
          0.3303379416465759,
          0.0
        ],
        [
          0.4604896605014801,
          0.3422379195690155,
          0.0
        ],
        [
          0.4604896605014801,
          0.33713793754577637,
          0.0
        ],
        [
          0.4604896605014801,
          0.33373793959617615,
          0.0
        ],
        [
          0.4604896605014801,
          0.33203792572021484,
          0.0
        ]
      ],
      "hand_center": [
        0.4710943102836609,
        0.33195698261260986,
        0.0
      ],
      "openness": 2.3032357692718506,
      "palm_size": 0.01612761616706848,
      "scale_hint": 0.24,
      "anchors": {
        "forehead": [
          0.5,
          0.23999999463558197,
          0.0
        ],
        "mouth": [
          0.5,
          0.3499999940395355,
          0.0
        ],
        "chin": [
          0.5,
          0.41999998688697815,
          0.0
        ],
        "left_shoulder": [
          0.3799999952316284,
          0.6200000047683716,
          0.0
        ],
        "right_shoulder": [
          0.6200000047683716,
          0.6200000047683716,
          0.0
        ],
        "shoulder_center": [
          0.5,
          0.6200000047683716,
          0.0
        ],
        "nose": [
          0.5,
          0.3100000023841858,
          0.0
        ],
        "scale_hint": 0.24
      }
    },
    {
      "handedness": "right",
      "hand_landmarks": [
        [
          0.4713793098926544,
          0.3582758605480194,
          0.0
        ],
        [
          0.47817930579185486,
          0.3565758466720581,
          0.0
        ],
        [
          0.4815793037414551,
          0.3531758487224579,
          0.0
        ],
        [
          0.4849793016910553,
          0.34977585077285767,
          0.0
        ],
        [
          0.4900793135166168,
          0.34807586669921875,
          0.0
        ],
        [
          0.47647932171821594,
          0.3412758708000183,
          0.0
        ],
        [
          0.47647932171821594,
          0.3208758533000946,
          0.0
        ],
        [
          0.47647932171821594,
          0.29707586765289307,
          0.0
        ],
        [
          0.47647932171821594,
          0.2698758542537689,
          0.0
        ],
        [
          0.4713793098926544,
          0.34467586874961853,
          0.0
        ],
        [
          0.4713793098926544,
          0.3378758728504181,
          0.0
        ],
        [
          0.4713793098926544,
          0.33277586102485657,
          0.0
        ],
        [
          0.4713793098926544,
          0.33107584714889526,
          0.0
        ],
        [
          0.4662792980670929,
          0.34467586874961853,
          0.0
        ],
        [
          0.4662792980670929,
          0.339575856924057,
          0.0
        ],
        [
          0.4662792980670929,
          0.3361758589744568,
          0.0
        ],
        [
          0.4662792980670929,
          0.33447587490081787,
          0.0
        ],
        [
          0.46117931604385376,
          0.34637585282325745,
          0.0
        ],
        [
          0.46117931604385376,
          0.3412758708000183,
          0.0
        ],
        [
          0.46117931604385376,
          0.3378758728504181,
          0.0
        ],
        [
          0.46117931604385376,
          0.3361758589744568,
          0.0
        ]
      ],
      "hand_center": [
        0.47178417444229126,
        0.3360949158668518,
        0.0
      ],
      "openness": 2.3032357692718506,
      "palm_size": 0.01612761616706848,
      "scale_hint": 0.24,
      "anchors": {
        "forehead": [
          0.5,
          0.23999999463558197,
          0.0
        ],
        "mouth": [
          0.5,
          0.3499999940395355,
          0.0
        ],
        "chin": [
          0.5,
          0.41999998688697815,
          0.0
        ],
        "left_shoulder": [
          0.3799999952316284,
          0.6200000047683716,
          0.0
        ],
        "right_shoulder": [
          0.6200000047683716,
          0.6200000047683716,
          0.0
        ],
        "shoulder_center": [
          0.5,
          0.6200000047683716,
          0.0
        ],
        "nose": [
          0.5,
          0.3100000023841858,
          0.0
        ],
        "scale_hint": 0.24
      }
    },
    {
      "handedness": "right",
      "hand_landmarks": [
        [
          0.4720689654350281,
          0.36241379380226135,
          0.0
        ],
        [
          0.4788689613342285,
          0.36071377992630005,
          0.0
        ],
        [
          0.48226895928382874,
          0.35731378197669983,
          0.0
        ],
        [
          0.48566895723342896,
          0.3539137840270996,
          0.0
        ],
        [
          0.4907689690589905,
          0.3522137999534607,
          0.0
        ],
        [
          0.4771689772605896,
          0.34541380405426025,
          0.0
        ],
        [
          0.4771689772605896,
          0.32501378655433655,
          0.0
        ],
        [
          0.4771689772605896,
          0.301213800907135,
          0.0
        ],
        [
          0.4771689772605896,
          0.27401378750801086,
          0.0
        ],
        [
          0.4720689654350281,
          0.3488138020038605,
          0.0
        ],
        [
          0.4720689654350281,
          0.34201380610466003,
          0.0
        ],
        [
          0.4720689654350281,
          0.3369137942790985,
          0.0
        ],
        [
          0.4720689654350281,
          0.3352137804031372,
          0.0
        ],
        [
          0.46696895360946655,
          0.3488138020038605,
          0.0
        ],
        [
          0.46696895360946655,
          0.34371379017829895,
          0.0
        ],
        [
          0.46696895360946655,
          0.34031379222869873,
          0.0
        ],
        [
          0.46696895360946655,
          0.3386138081550598,
          0.0
        ],
        [
          0.4618689715862274,
          0.3505137860774994,
          0.0
        ],
        [
          0.4618689715862274,
          0.34541380405426025,
          0.0
        ],
        [
          0.4618689715862274,
          0.34201380610466003,
          0.0
        ],
        [
          0.4618689715862274,
          0.34031379222869873,
          0.0
        ]
      ],
      "hand_center": [
        0.47247374057769775,
        0.34023287892341614,
        0.0
      ],
      "openness": 2.3032357692718506,
      "palm_size": 0.01612761616706848,
      "scale_hint": 0.24,
      "anchors": {
        "forehead": [
          0.5,
          0.23999999463558197,
          0.0
        ],
        "mouth": [
          0.5,
          0.3499999940395355,
          0.0
        ],
        "chin": [
          0.5,
          0.41999998688697815,
          0.0
        ],
        "left_shoulder": [
          0.3799999952316284,
          0.6200000047683716,
          0.0
        ],
        "right_shoulder": [
          0.6200000047683716,
          0.6200000047683716,
          0.0
        ],
        "shoulder_center": [
          0.5,
          0.6200000047683716,
          0.0
        ],
        "nose": [
          0.5,
          0.3100000023841858,
          0.0
        ],
        "scale_hint": 0.24
      }
    },
    {
      "handedness": "right",
      "hand_landmarks": [
        [
          0.47275862097740173,
          0.3665517270565033,
          0.0
        ],
        [
          0.4795586168766022,
          0.364851713180542,
          0.0
        ],
        [
          0.4829586148262024,
          0.3614517152309418,
          0.0
        ],
        [
          0.4863586127758026,
          0.35805171728134155,
          0.0
        ],
        [
          0.49145862460136414,
          0.35635173320770264,
          0.0
        ],
        [
          0.47785863280296326,
          0.3495517373085022,
          0.0
        ],
        [
          0.47785863280296326,
          0.3291517198085785,
          0.0
        ],
        [
          0.47785863280296326,
          0.30535173416137695,
          0.0
        ],
        [
          0.47785863280296326,
          0.2781517207622528,
          0.0
        ],
        [
          0.47275862097740173,
          0.3529517352581024,
          0.0
        ],
        [
          0.47275862097740173,
          0.346151739358902,
          0.0
        ],
        [
          0.47275862097740173,
          0.34105172753334045,
          0.0
        ],
        [
          0.47275862097740173,
          0.33935171365737915,
          0.0
        ],
        [
          0.4676586091518402,
          0.3529517352581024,
          0.0
        ],
        [
          0.4676586091518402,
          0.3478517234325409,
          0.0
        ],
        [
          0.4676586091518402,
          0.3444517254829407,
          0.0
        ],
        [
          0.4676586091518402,
          0.34275174140930176,
          0.0
        ],
        [
          0.4625586271286011,
          0.35465171933174133,
          0.0
        ],
        [
          0.4625586271286011,
          0.3495517373085022,
          0.0
        ],
        [
          0.4625586271286011,
          0.346151739358902,
          0.0
        ],
        [
          0.4625586271286011,
          0.3444517254829407,
          0.0
        ]
      ],
      "hand_center": [
        0.4731634259223938,
        0.3443708121776581,
        0.0
      ],
      "openness": 2.3032357692718506,
      "palm_size": 0.01612761616706848,
      "scale_hint": 0.24,
      "anchors": {
        "forehead": [
          0.5,
          0.23999999463558197,
          0.0
        ],
        "mouth": [
          0.5,
          0.3499999940395355,
          0.0
        ],
        "chin": [
          0.5,
          0.41999998688697815,
          0.0
        ],
        "left_shoulder": [
          0.3799999952316284,
          0.6200000047683716,
          0.0
        ],
        "right_shoulder": [
          0.6200000047683716,
          0.6200000047683716,
          0.0
        ],
        "shoulder_center": [
          0.5,
          0.6200000047683716,
          0.0
        ],
        "nose": [
          0.5,
          0.3100000023841858,
          0.0
        ],
        "scale_hint": 0.24
      }
    },
    {
      "handedness": "right",
      "hand_landmarks": [
        [
          0.4734482765197754,
          0.37068966031074524,
          0.0
        ],
        [
          0.48024827241897583,
          0.36898964643478394,
          0.0
        ],
        [
          0.48364827036857605,
          0.3655896484851837,
          0.0
        ],
        [
          0.48704826831817627,
          0.3621896505355835,
          0.0
        ],
        [
          0.4921482801437378,
          0.3604896664619446,
          0.0
        ],
        [
          0.4785482883453369,
          0.35368967056274414,
          0.0
        ],
        [
          0.4785482883453369,
          0.33328965306282043,
          0.0
        ],
        [
          0.4785482883453369,
          0.3094896674156189,
          0.0
        ],
        [
          0.4785482883453369,
          0.28228965401649475,
          0.0
        ],
        [
          0.4734482765197754,
          0.35708966851234436,
          0.0
        ],
        [
          0.4734482765197754,
          0.3502896726131439,
          0.0
        ],
        [
          0.4734482765197754,
          0.3451896607875824,
          0.0
        ],
        [
          0.4734482765197754,
          0.3434896469116211,
          0.0
        ],
        [
          0.46834826469421387,
          0.35708966851234436,
          0.0
        ],
        [
          0.46834826469421387,
          0.35198965668678284,
          0.0
        ],
        [
          0.46834826469421387,
          0.3485896587371826,
          0.0
        ],
        [
          0.46834826469421387,
          0.3468896746635437,
          0.0
        ],
        [
          0.46324828267097473,
          0.3587896525859833,
          0.0
        ],
        [
          0.46324828267097473,
          0.35368967056274414,
          0.0
        ],
        [
          0.46324828267097473,
          0.3502896726131439,
          0.0
        ],
        [
          0.46324828267097473,
          0.3485896587371826,
          0.0
        ]
      ],
      "hand_center": [
        0.47385305166244507,
        0.34850868582725525,
        0.0
      ],
      "openness": 2.3032357692718506,
      "palm_size": 0.01612761616706848,
      "scale_hint": 0.24,
      "anchors": {
        "forehead": [
          0.5,
          0.23999999463558197,
          0.0
        ],
        "mouth": [
          0.5,
          0.3499999940395355,
          0.0
        ],
        "chin": [
          0.5,
          0.41999998688697815,
          0.0
        ],
        "left_shoulder": [
          0.3799999952316284,
          0.6200000047683716,
          0.0
        ],
        "right_shoulder": [
          0.6200000047683716,
          0.6200000047683716,
          0.0
        ],
        "shoulder_center": [
          0.5,
          0.6200000047683716,
          0.0
        ],
        "nose": [
          0.5,
          0.3100000023841858,
          0.0
        ],
        "scale_hint": 0.24
      }
    },
    {
      "handedness": "right",
      "hand_landmarks": [
        [
          0.47413793206214905,
          0.3748275935649872,
          0.0
        ],
        [
          0.4809379279613495,
          0.3731275796890259,
          0.0
        ],
        [
          0.4843379259109497,
          0.36972758173942566,
          0.0
        ],
        [
          0.4877379238605499,
          0.36632758378982544,
          0.0
        ],
        [
          0.49283793568611145,
          0.3646275997161865,
          0.0
        ],
        [
          0.47923794388771057,
          0.3578276038169861,
          0.0
        ],
        [
          0.47923794388771057,
          0.3374275863170624,
          0.0
        ],
        [
          0.47923794388771057,
          0.31362760066986084,
          0.0
        ],
        [
          0.47923794388771057,
          0.2864275872707367,
          0.0
        ],
        [
          0.47413793206214905,
          0.3612276017665863,
          0.0
        ],
        [
          0.47413793206214905,
          0.35442760586738586,
          0.0
        ],
        [
          0.47413793206214905,
          0.34932759404182434,
          0.0
        ],
        [
          0.47413793206214905,
          0.34762758016586304,
          0.0
        ],
        [
          0.4690379202365875,
          0.3612276017665863,
          0.0
        ],
        [
          0.4690379202365875,
          0.3561275899410248,
          0.0
        ],
        [
          0.4690379202365875,
          0.35272759199142456,
          0.0
        ],
        [
          0.4690379202365875,
          0.35102760791778564,
          0.0
        ],
        [
          0.4639379382133484,
          0.3629275858402252,
          0.0
        ],
        [
          0.4639379382133484,
          0.3578276038169861,
          0.0
        ],
        [
          0.4639379382133484,
          0.35442760586738586,
          0.0
        ],
        [
          0.4639379382133484,
          0.35272759199142456,
          0.0
        ]
      ],
      "hand_center": [
        0.47454267740249634,
        0.3526466488838196,
        0.0
      ],
      "openness": 2.3032357692718506,
      "palm_size": 0.01612761616706848,
      "scale_hint": 0.24,
      "anchors": {
        "forehead": [
          0.5,
          0.23999999463558197,
          0.0
        ],
        "mouth": [
          0.5,
          0.3499999940395355,
          0.0
        ],
        "chin": [
          0.5,
          0.41999998688697815,
          0.0
        ],
        "left_shoulder": [
          0.3799999952316284,
          0.6200000047683716,
          0.0
        ],
        "right_shoulder": [
          0.6200000047683716,
          0.6200000047683716,
          0.0
        ],
        "shoulder_center": [
          0.5,
          0.6200000047683716,
          0.0
        ],
        "nose": [
          0.5,
          0.3100000023841858,
          0.0
        ],
        "scale_hint": 0.24
      }
    },
    {
      "handedness": "right",
      "hand_landmarks": [
        [
          0.4748275876045227,
          0.37896549701690674,
          0.0
        ],
        [
          0.48162758350372314,
          0.37726548314094543,
          0.0
        ],
        [
          0.48502758145332336,
          0.3738654851913452,
          0.0
        ],
        [
          0.4884275794029236,
          0.370465487241745,
          0.0
        ],
        [
          0.4935275912284851,
          0.3687655031681061,
          0.0
        ],
        [
          0.47992759943008423,
          0.36196550726890564,
          0.0
        ],
        [
          0.47992759943008423,
          0.34156548976898193,
          0.0
        ],
        [
          0.47992759943008423,
          0.3177655041217804,
          0.0
        ],
        [
          0.47992759943008423,
          0.29056549072265625,
          0.0
        ],
        [
          0.4748275876045227,
          0.36536550521850586,
          0.0
        ],
        [
          0.4748275876045227,
          0.3585655093193054,
          0.0
        ],
        [
          0.4748275876045227,
          0.3534654974937439,
          0.0
        ],
        [
          0.4748275876045227,
          0.3517654836177826,
          0.0
        ],
        [
          0.4697275757789612,
          0.36536550521850586,
          0.0
        ],
        [
          0.4697275757789612,
          0.36026549339294434,
          0.0
        ],
        [
          0.4697275757789612,
          0.3568654954433441,
          0.0
        ],
        [
          0.4697275757789612,
          0.3551654815673828,
          0.0
        ],
        [
          0.46462759375572205,
          0.3670654892921448,
          0.0
        ],
        [
          0.46462759375572205,
          0.36196550726890564,
          0.0
        ],
        [
          0.46462759375572205,
          0.3585655093193054,
          0.0
        ],
        [
          0.46462759375572205,
          0.3568654954433441,
          0.0
        ]
      ],
      "hand_center": [
        0.4752323031425476,
        0.35678452253341675,
        0.0
      ],
      "openness": 2.303236246109009,
      "palm_size": 0.01612761616706848,
      "scale_hint": 0.24,
      "anchors": {
        "forehead": [
          0.5,
          0.23999999463558197,
          0.0
        ],
        "mouth": [
          0.5,
          0.3499999940395355,
          0.0
        ],
        "chin": [
          0.5,
          0.41999998688697815,
          0.0
        ],
        "left_shoulder": [
          0.3799999952316284,
          0.6200000047683716,
          0.0
        ],
        "right_shoulder": [
          0.6200000047683716,
          0.6200000047683716,
          0.0
        ],
        "shoulder_center": [
          0.5,
          0.6200000047683716,
          0.0
        ],
        "nose": [
          0.5,
          0.3100000023841858,
          0.0
        ],
        "scale_hint": 0.24
      }
    },
    {
      "handedness": "right",
      "hand_landmarks": [
        [
          0.47551724314689636,
          0.3831034302711487,
          0.0
        ],
        [
          0.4823172390460968,
          0.3814034163951874,
          0.0
        ],
        [
          0.485717236995697,
          0.37800341844558716,
          0.0
        ],
        [
          0.48911723494529724,
          0.37460342049598694,
          0.0
        ],
        [
          0.49421724677085876,
          0.372903436422348,
          0.0
        ],
        [
          0.4806172549724579,
          0.3661034405231476,
          0.0
        ],
        [
          0.4806172549724579,
          0.3457034230232239,
          0.0
        ],
        [
          0.4806172549724579,
          0.32190343737602234,
          0.0
        ],
        [
          0.4806172549724579,
          0.2947034239768982,
          0.0
        ],
        [
          0.47551724314689636,
          0.3695034384727478,
          0.0
        ],
        [
          0.47551724314689636,
          0.36270344257354736,
          0.0
        ],
        [
          0.47551724314689636,
          0.35760343074798584,
          0.0
        ],
        [
          0.47551724314689636,
          0.35590341687202454,
          0.0
        ],
        [
          0.47041723132133484,
          0.3695034384727478,
          0.0
        ],
        [
          0.47041723132133484,
          0.3644034266471863,
          0.0
        ],
        [
          0.47041723132133484,
          0.36100342869758606,
          0.0
        ],
        [
          0.47041723132133484,
          0.35930341482162476,
          0.0
        ],
        [
          0.4653172492980957,
          0.3712034225463867,
          0.0
        ],
        [
          0.4653172492980957,
          0.3661034405231476,
          0.0
        ],
        [
          0.4653172492980957,
          0.36270344257354736,
          0.0
        ],
        [
          0.4653172492980957,
          0.36100342869758606,
          0.0
        ]
      ],
      "hand_center": [
        0.4759218990802765,
        0.3609224855899811,
        0.0
      ],
      "openness": 2.303236246109009,
      "palm_size": 0.01612761616706848,
      "scale_hint": 0.24,
      "anchors": {
        "forehead": [
          0.5,
          0.23999999463558197,
          0.0
        ],
        "mouth": [
          0.5,
          0.3499999940395355,
          0.0
        ],
        "chin": [
          0.5,
          0.41999998688697815,
          0.0
        ],
        "left_shoulder": [
          0.3799999952316284,
          0.6200000047683716,
          0.0
        ],
        "right_shoulder": [
          0.6200000047683716,
          0.6200000047683716,
          0.0
        ],
        "shoulder_center": [
          0.5,
          0.6200000047683716,
          0.0
        ],
        "nose": [
          0.5,
          0.3100000023841858,
          0.0
        ],
        "scale_hint": 0.24
      }
    },
    {
      "handedness": "right",
      "hand_landmarks": [
        [
          0.47620689868927,
          0.3872413635253906,
          0.0
        ],
        [
          0.48300689458847046,
          0.3855413496494293,
          0.0
        ],
        [
          0.4864068925380707,
          0.3821413516998291,
          0.0
        ],
        [
          0.4898068904876709,
          0.3787413537502289,
          0.0
        ],
        [
          0.4949069023132324,
          0.37704136967658997,
          0.0
        ],
        [
          0.48130691051483154,
          0.3702413737773895,
          0.0
        ],
        [
          0.48130691051483154,
          0.3498413562774658,
          0.0
        ],
        [
          0.48130691051483154,
          0.3260413706302643,
          0.0
        ],
        [
          0.48130691051483154,
          0.29884135723114014,
          0.0
        ],
        [
          0.47620689868927,
          0.37364137172698975,
          0.0
        ],
        [
          0.47620689868927,
          0.3668413758277893,
          0.0
        ],
        [
          0.47620689868927,
          0.3617413640022278,
          0.0
        ],
        [
          0.47620689868927,
          0.3600413501262665,
          0.0
        ],
        [
          0.4711068868637085,
          0.37364137172698975,
          0.0
        ],
        [
          0.4711068868637085,
          0.3685413599014282,
          0.0
        ],
        [
          0.4711068868637085,
          0.365141361951828,
          0.0
        ],
        [
          0.4711068868637085,
          0.3634413480758667,
          0.0
        ],
        [
          0.46600690484046936,
          0.37534135580062866,
          0.0
        ],
        [
          0.46600690484046936,
          0.3702413737773895,
          0.0
        ],
        [
          0.46600690484046936,
          0.3668413758277893,
          0.0
        ],
        [
          0.46600690484046936,
          0.365141361951828,
          0.0
        ]
      ],
      "hand_center": [
        0.4766117334365845,
        0.365060418844223,
        0.0
      ],
      "openness": 2.303236246109009,
      "palm_size": 0.01612761616706848,
      "scale_hint": 0.24,
      "anchors": {
        "forehead": [
          0.5,
          0.23999999463558197,
          0.0
        ],
        "mouth": [
          0.5,
          0.3499999940395355,
          0.0
        ],
        "chin": [
          0.5,
          0.41999998688697815,
          0.0
        ],
        "left_shoulder": [
          0.3799999952316284,
          0.6200000047683716,
          0.0
        ],
        "right_shoulder": [
          0.6200000047683716,
          0.6200000047683716,
          0.0
        ],
        "shoulder_center": [
          0.5,
          0.6200000047683716,
          0.0
        ],
        "nose": [
          0.5,
          0.3100000023841858,
          0.0
        ],
        "scale_hint": 0.24
      }
    },
    {
      "handedness": "right",
      "hand_landmarks": [
        [
          0.4768965542316437,
          0.39137929677963257,
          0.0
        ],
        [
          0.4836965501308441,
          0.38967928290367126,
          0.0
        ],
        [
          0.48709654808044434,
          0.38627928495407104,
          0.0
        ],
        [
          0.49049654603004456,
          0.3828792870044708,
          0.0
        ],
        [
          0.4955965578556061,
          0.3811793029308319,
          0.0
        ],
        [
          0.4819965660572052,
          0.37437930703163147,
          0.0
        ],
        [
          0.4819965660572052,
          0.35397928953170776,
          0.0
        ],
        [
          0.4819965660572052,
          0.3301793038845062,
          0.0
        ],
        [
          0.4819965660572052,
          0.3029792904853821,
          0.0
        ],
        [
          0.4768965542316437,
          0.3777793049812317,
          0.0
        ],
        [
          0.4768965542316437,
          0.37097930908203125,
          0.0
        ],
        [
          0.4768965542316437,
          0.3658792972564697,
          0.0
        ],
        [
          0.4768965542316437,
          0.3641792833805084,
          0.0
        ],
        [
          0.47179654240608215,
          0.3777793049812317,
          0.0
        ],
        [
          0.47179654240608215,
          0.37267929315567017,
          0.0
        ],
        [
          0.47179654240608215,
          0.36927929520606995,
          0.0
        ],
        [
          0.47179654240608215,
          0.36757928133010864,
          0.0
        ],
        [
          0.466696560382843,
          0.3794792890548706,
          0.0
        ],
        [
          0.466696560382843,
          0.37437930703163147,
          0.0
        ],
        [
          0.466696560382843,
          0.37097930908203125,
          0.0
        ],
        [
          0.466696560382843,
          0.36927929520606995,
          0.0
        ]
      ],
      "hand_center": [
        0.4773014187812805,
        0.36919838190078735,
        0.0
      ],
      "openness": 2.303236246109009,
      "palm_size": 0.01612761616706848,
      "scale_hint": 0.24,
      "anchors": {
        "forehead": [
          0.5,
          0.23999999463558197,
          0.0
        ],
        "mouth": [
          0.5,
          0.3499999940395355,
          0.0
        ],
        "chin": [
          0.5,
          0.41999998688697815,
          0.0
        ],
        "left_shoulder": [
          0.3799999952316284,
          0.6200000047683716,
          0.0
        ],
        "right_shoulder": [
          0.6200000047683716,
          0.6200000047683716,
          0.0
        ],
        "shoulder_center": [
          0.5,
          0.6200000047683716,
          0.0
        ],
        "nose": [
          0.5,
          0.3100000023841858,
          0.0
        ],
        "scale_hint": 0.24
      }
    },
    {
      "handedness": "right",
      "hand_landmarks": [
        [
          0.47758620977401733,
          0.3955172300338745,
          0.0
        ],
        [
          0.4843862056732178,
          0.3938172161579132,
          0.0
        ],
        [
          0.487786203622818,
          0.390417218208313,
          0.0
        ],
        [
          0.4911862015724182,
          0.38701722025871277,
          0.0
        ],
        [
          0.49628621339797974,
          0.38531723618507385,
          0.0
        ],
        [
          0.48268622159957886,
          0.3785172402858734,
          0.0
        ],
        [
          0.48268622159957886,
          0.3581172227859497,
          0.0
        ],
        [
          0.48268622159957886,
          0.33431723713874817,
          0.0
        ],
        [
          0.48268622159957886,
          0.307117223739624,
          0.0
        ],
        [
          0.47758620977401733,
          0.38191723823547363,
          0.0
        ],
        [
          0.47758620977401733,
          0.3751172423362732,
          0.0
        ],
        [
          0.47758620977401733,
          0.37001723051071167,
          0.0
        ],
        [
          0.47758620977401733,
          0.36831721663475037,
          0.0
        ],
        [
          0.4724861979484558,
          0.38191723823547363,
          0.0
        ],
        [
          0.4724861979484558,
          0.3768172264099121,
          0.0
        ],
        [
          0.4724861979484558,
          0.3734172284603119,
          0.0
        ],
        [
          0.4724861979484558,
          0.3717172145843506,
          0.0
        ],
        [
          0.4673862159252167,
          0.38361722230911255,
          0.0
        ],
        [
          0.4673862159252167,
          0.3785172402858734,
          0.0
        ],
        [
          0.4673862159252167,
          0.3751172423362732,
          0.0
        ],
        [
          0.4673862159252167,
          0.3734172284603119,
          0.0
        ]
      ],
      "hand_center": [
        0.4779909551143646,
        0.3733363151550293,
        0.0
      ],
      "openness": 2.303236246109009,
      "palm_size": 0.01612761616706848,
      "scale_hint": 0.24,
      "anchors": {
        "forehead": [
          0.5,
          0.23999999463558197,
          0.0
        ],
        "mouth": [
          0.5,
          0.3499999940395355,
          0.0
        ],
        "chin": [
          0.5,
          0.41999998688697815,
          0.0
        ],
        "left_shoulder": [
          0.3799999952316284,
          0.6200000047683716,
          0.0
        ],
        "right_shoulder": [
          0.6200000047683716,
          0.6200000047683716,
          0.0
        ],
        "shoulder_center": [
          0.5,
          0.6200000047683716,
          0.0
        ],
        "nose": [
          0.5,
          0.3100000023841858,
          0.0
        ],
        "scale_hint": 0.24
      }
    },
    {
      "handedness": "right",
      "hand_landmarks": [
        [
          0.478275865316391,
          0.39965516328811646,
          0.0
        ],
        [
          0.48507586121559143,
          0.39795514941215515,
          0.0
        ],
        [
          0.48847585916519165,
          0.39455515146255493,
          0.0
        ],
        [
          0.49187585711479187,
          0.3911551535129547,
          0.0
        ],
        [
          0.4969758689403534,
          0.3894551694393158,
          0.0
        ],
        [
          0.4833758771419525,
          0.38265517354011536,
          0.0
        ],
        [
          0.4833758771419525,
          0.36225515604019165,
          0.0
        ],
        [
          0.4833758771419525,
          0.3384551703929901,
          0.0
        ],
        [
          0.4833758771419525,
          0.31125515699386597,
          0.0
        ],
        [
          0.478275865316391,
          0.3860551714897156,
          0.0
        ],
        [
          0.478275865316391,
          0.37925517559051514,
          0.0
        ],
        [
          0.478275865316391,
          0.3741551637649536,
          0.0
        ],
        [
          0.478275865316391,
          0.3724551498889923,
          0.0
        ],
        [
          0.47317585349082947,
          0.3860551714897156,
          0.0
        ],
        [
          0.47317585349082947,
          0.38095515966415405,
          0.0
        ],
        [
          0.47317585349082947,
          0.37755516171455383,
          0.0
        ],
        [
          0.47317585349082947,
          0.37585514783859253,
          0.0
        ],
        [
          0.46807587146759033,
          0.3877551555633545,
          0.0
        ],
        [
          0.46807587146759033,
          0.38265517354011536,
          0.0
        ],
        [
          0.46807587146759033,
          0.37925517559051514,
          0.0
        ],
        [
          0.46807587146759033,
          0.37755516171455383,
          0.0
        ]
      ],
      "hand_center": [
        0.4786806106567383,
        0.37747421860694885,
        0.0
      ],
      "openness": 2.303236246109009,
      "palm_size": 0.01612761616706848,
      "scale_hint": 0.24,
      "anchors": {
        "forehead": [
          0.5,
          0.23999999463558197,
          0.0
        ],
        "mouth": [
          0.5,
          0.3499999940395355,
          0.0
        ],
        "chin": [
          0.5,
          0.41999998688697815,
          0.0
        ],
        "left_shoulder": [
          0.3799999952316284,
          0.6200000047683716,
          0.0
        ],
        "right_shoulder": [
          0.6200000047683716,
          0.6200000047683716,
          0.0
        ],
        "shoulder_center": [
          0.5,
          0.6200000047683716,
          0.0
        ],
        "nose": [
          0.5,
          0.3100000023841858,
          0.0
        ],
        "scale_hint": 0.24
      }
    },
    {
      "handedness": "right",
      "hand_landmarks": [
        [
          0.47896552085876465,
          0.4037930965423584,
          0.0
        ],
        [
          0.4857655167579651,
          0.4020930826663971,
          0.0
        ],
        [
          0.4891655147075653,
          0.3986930847167969,
          0.0
        ],
        [
          0.4925655126571655,
          0.39529308676719666,
          0.0
        ],
        [
          0.49766552448272705,
          0.39359310269355774,
          0.0
        ],
        [
          0.48406553268432617,
          0.3867931067943573,
          0.0
        ],
        [
          0.48406553268432617,
          0.3663930892944336,
          0.0
        ],
        [
          0.48406553268432617,
          0.34259310364723206,
          0.0
        ],
        [
          0.48406553268432617,
          0.3153930902481079,
          0.0
        ],
        [
          0.47896552085876465,
          0.3901931047439575,
          0.0
        ],
        [
          0.47896552085876465,
          0.3833931088447571,
          0.0
        ],
        [
          0.47896552085876465,
          0.37829309701919556,
          0.0
        ],
        [
          0.47896552085876465,
          0.37659308314323425,
          0.0
        ],
        [
          0.4738655090332031,
          0.3901931047439575,
          0.0
        ],
        [
          0.4738655090332031,
          0.385093092918396,
          0.0
        ],
        [
          0.4738655090332031,
          0.3816930949687958,
          0.0
        ],
        [
          0.4738655090332031,
          0.3799930810928345,
          0.0
        ],
        [
          0.468765527009964,
          0.39189308881759644,
          0.0
        ],
        [
          0.468765527009964,
          0.3867931067943573,
          0.0
        ],
        [
          0.468765527009964,
          0.3833931088447571,
          0.0
        ],
        [
          0.468765527009964,
          0.3816930949687958,
          0.0
        ]
      ],
      "hand_center": [
        0.47937026619911194,
        0.3816121518611908,
        0.0
      ],
      "openness": 2.303236246109009,
      "palm_size": 0.01612761616706848,
      "scale_hint": 0.24,
      "anchors": {
        "forehead": [
          0.5,
          0.23999999463558197,
          0.0
        ],
        "mouth": [
          0.5,
          0.3499999940395355,
          0.0
        ],
        "chin": [
          0.5,
          0.41999998688697815,
          0.0
        ],
        "left_shoulder": [
          0.3799999952316284,
          0.6200000047683716,
          0.0
        ],
        "right_shoulder": [
          0.6200000047683716,
          0.6200000047683716,
          0.0
        ],
        "shoulder_center": [
          0.5,
          0.6200000047683716,
          0.0
        ],
        "nose": [
          0.5,
          0.3100000023841858,
          0.0
        ],
        "scale_hint": 0.24
      }
    },
    {
      "handedness": "right",
      "hand_landmarks": [
        [
          0.4796551764011383,
          0.40793102979660034,
          0.0
        ],
        [
          0.48645517230033875,
          0.40623101592063904,
          0.0
        ],
        [
          0.48985517024993896,
          0.4028310179710388,
          0.0
        ],
        [
          0.4932551681995392,
          0.3994310200214386,
          0.0
        ],
        [
          0.4983551800251007,
          0.3977310359477997,
          0.0
        ],
        [
          0.48475518822669983,
          0.39093104004859924,
          0.0
        ],
        [
          0.48475518822669983,
          0.37053102254867554,
          0.0
        ],
        [
          0.48475518822669983,
          0.346731036901474,
          0.0
        ],
        [
          0.48475518822669983,
          0.31953102350234985,
          0.0
        ],
        [
          0.4796551764011383,
          0.39433103799819946,
          0.0
        ],
        [
          0.4796551764011383,
          0.387531042098999,
          0.0
        ],
        [
          0.4796551764011383,
          0.3824310302734375,
          0.0
        ],
        [
          0.4796551764011383,
          0.3807310163974762,
          0.0
        ],
        [
          0.4745551645755768,
          0.39433103799819946,
          0.0
        ],
        [
          0.4745551645755768,
          0.38923102617263794,
          0.0
        ],
        [
          0.4745551645755768,
          0.3858310282230377,
          0.0
        ],
        [
          0.4745551645755768,
          0.3841310143470764,
          0.0
        ],
        [
          0.46945518255233765,
          0.3960310220718384,
          0.0
        ],
        [
          0.46945518255233765,
          0.39093104004859924,
          0.0
        ],
        [
          0.46945518255233765,
          0.387531042098999,
          0.0
        ],
        [
          0.46945518255233765,
          0.3858310282230377,
          0.0
        ]
      ],
      "hand_center": [
        0.4800598621368408,
        0.38575008511543274,
        0.0
      ],
      "openness": 2.303236246109009,
      "palm_size": 0.01612761616706848,
      "scale_hint": 0.24,
      "anchors": {
        "forehead": [
          0.5,
          0.23999999463558197,
          0.0
        ],
        "mouth": [
          0.5,
          0.3499999940395355,
          0.0
        ],
        "chin": [
          0.5,
          0.41999998688697815,
          0.0
        ],
        "left_shoulder": [
          0.3799999952316284,
          0.6200000047683716,
          0.0
        ],
        "right_shoulder": [
          0.6200000047683716,
          0.6200000047683716,
          0.0
        ],
        "shoulder_center": [
          0.5,
          0.6200000047683716,
          0.0
        ],
        "nose": [
          0.5,
          0.3100000023841858,
          0.0
        ],
        "scale_hint": 0.24
      }
    },
    {
      "handedness": "right",
      "hand_landmarks": [
        [
          0.48034483194351196,
          0.4120689630508423,
          0.0
        ],
        [
          0.4871448278427124,
          0.410368949174881,
          0.0
        ],
        [
          0.4905448257923126,
          0.40696895122528076,
          0.0
        ],
        [
          0.49394482374191284,
          0.40356895327568054,
          0.0
        ],
        [
          0.49904483556747437,
          0.4018689692020416,
          0.0
        ],
        [
          0.4854448437690735,
          0.3950689733028412,
          0.0
        ],
        [
          0.4854448437690735,
          0.3746689558029175,
          0.0
        ],
        [
          0.4854448437690735,
          0.35086897015571594,
          0.0
        ],
        [
          0.4854448437690735,
          0.3236689567565918,
          0.0
        ],
        [
          0.48034483194351196,
          0.3984689712524414,
          0.0
        ],
        [
          0.48034483194351196,
          0.39166897535324097,
          0.0
        ],
        [
          0.48034483194351196,
          0.38656896352767944,
          0.0
        ],
        [
          0.48034483194351196,
          0.38486894965171814,
          0.0
        ],
        [
          0.47524482011795044,
          0.3984689712524414,
          0.0
        ],
        [
          0.47524482011795044,
          0.3933689594268799,
          0.0
        ],
        [
          0.47524482011795044,
          0.38996896147727966,
          0.0
        ],
        [
          0.47524482011795044,
          0.38826894760131836,
          0.0
        ],
        [
          0.4701448380947113,
          0.4001689553260803,
          0.0
        ],
        [
          0.4701448380947113,
          0.3950689733028412,
          0.0
        ],
        [
          0.4701448380947113,
          0.39166897535324097,
          0.0
        ],
        [
          0.4701448380947113,
          0.38996896147727966,
          0.0
        ]
      ],
      "hand_center": [
        0.4807496666908264,
        0.38988804817199707,
        0.0
      ],
      "openness": 2.303236246109009,
      "palm_size": 0.01612761616706848,
      "scale_hint": 0.24,
      "anchors": {
        "forehead": [
          0.5,
          0.23999999463558197,
          0.0
        ],
        "mouth": [
          0.5,
          0.3499999940395355,
          0.0
        ],
        "chin": [
          0.5,
          0.41999998688697815,
          0.0
        ],
        "left_shoulder": [
          0.3799999952316284,
          0.6200000047683716,
          0.0
        ],
        "right_shoulder": [
          0.6200000047683716,
          0.6200000047683716,
          0.0
        ],
        "shoulder_center": [
          0.5,
          0.6200000047683716,
          0.0
        ],
        "nose": [
          0.5,
          0.3100000023841858,
          0.0
        ],
        "scale_hint": 0.24
      }
    },
    {
      "handedness": "right",
      "hand_landmarks": [
        [
          0.4810344874858856,
          0.41620689630508423,
          0.0
        ],
        [
          0.48783448338508606,
          0.4145068824291229,
          0.0
        ],
        [
          0.4912344813346863,
          0.4111068844795227,
          0.0
        ],
        [
          0.4946344792842865,
          0.4077068865299225,
          0.0
        ],
        [
          0.499734491109848,
          0.40600690245628357,
          0.0
        ],
        [
          0.48613449931144714,
          0.39920690655708313,
          0.0
        ],
        [
          0.48613449931144714,
          0.3788068890571594,
          0.0
        ],
        [
          0.48613449931144714,
          0.3550069034099579,
          0.0
        ],
        [
          0.48613449931144714,
          0.32780689001083374,
          0.0
        ],
        [
          0.4810344874858856,
          0.40260690450668335,
          0.0
        ],
        [
          0.4810344874858856,
          0.3958069086074829,
          0.0
        ],
        [
          0.4810344874858856,
          0.3907068967819214,
          0.0
        ],
        [
          0.4810344874858856,
          0.3890068829059601,
          0.0
        ],
        [
          0.4759344756603241,
          0.40260690450668335,
          0.0
        ],
        [
          0.4759344756603241,
          0.3975068926811218,
          0.0
        ],
        [
          0.4759344756603241,
          0.3941068947315216,
          0.0
        ],
        [
          0.4759344756603241,
          0.3924068808555603,
          0.0
        ],
        [
          0.47083449363708496,
          0.40430688858032227,
          0.0
        ],
        [
          0.47083449363708496,
          0.39920690655708313,
          0.0
        ],
        [
          0.47083449363708496,
          0.3958069086074829,
          0.0
        ],
        [
          0.47083449363708496,
          0.3941068947315216,
          0.0
        ]
      ],
      "hand_center": [
        0.4814392626285553,
        0.394025981426239,
        0.0
      ],
      "openness": 2.303236246109009,
      "palm_size": 0.01612761616706848,
      "scale_hint": 0.24,
      "anchors": {
        "forehead": [
          0.5,
          0.23999999463558197,
          0.0
        ],
        "mouth": [
          0.5,
          0.3499999940395355,
          0.0
        ],
        "chin": [
          0.5,
          0.41999998688697815,
          0.0
        ],
        "left_shoulder": [
          0.3799999952316284,
          0.6200000047683716,
          0.0
        ],
        "right_shoulder": [
          0.6200000047683716,
          0.6200000047683716,
          0.0
        ],
        "shoulder_center": [
          0.5,
          0.6200000047683716,
          0.0
        ],
        "nose": [
          0.5,
          0.3100000023841858,
          0.0
        ],
        "scale_hint": 0.24
      }
    },
    {
      "handedness": "right",
      "hand_landmarks": [
        [
          0.4817241430282593,
          0.42034482955932617,
          0.0
        ],
        [
          0.4885241389274597,
          0.41864481568336487,
          0.0
        ],
        [
          0.49192413687705994,
          0.41524481773376465,
          0.0
        ],
        [
          0.49532413482666016,
          0.41184481978416443,
          0.0
        ],
        [
          0.5004241466522217,
          0.4101448357105255,
          0.0
        ],
        [
          0.4868241548538208,
          0.4033448398113251,
          0.0
        ],
        [
          0.4868241548538208,
          0.38294482231140137,
          0.0
        ],
        [
          0.4868241548538208,
          0.35914483666419983,
          0.0
        ],
        [
          0.4868241548538208,
          0.3319448232650757,
          0.0
        ],
        [
          0.4817241430282593,
          0.4067448377609253,
          0.0
        ],
        [
          0.4817241430282593,
          0.39994484186172485,
          0.0
        ],
        [
          0.4817241430282593,
          0.39484483003616333,
          0.0
        ],
        [
          0.4817241430282593,
          0.393144816160202,
          0.0
        ],
        [
          0.47662413120269775,
          0.4067448377609253,
          0.0
        ],
        [
          0.47662413120269775,
          0.40164482593536377,
          0.0
        ],
        [
          0.47662413120269775,
          0.39824482798576355,
          0.0
        ],
        [
          0.47662413120269775,
          0.39654481410980225,
          0.0
        ],
        [
          0.4715241491794586,
          0.4084448218345642,
          0.0
        ],
        [
          0.4715241491794586,
          0.4033448398113251,
          0.0
        ],
        [
          0.4715241491794586,
          0.39994484186172485,
          0.0
        ],
        [
          0.4715241491794586,
          0.39824482798576355,
          0.0
        ]
      ],
      "hand_center": [
        0.48212891817092896,
        0.39816388487815857,
        0.0
      ],
      "openness": 2.303236246109009,
      "palm_size": 0.01612761616706848,
      "scale_hint": 0.24,
      "anchors": {
        "forehead": [
          0.5,
          0.23999999463558197,
          0.0
        ],
        "mouth": [
          0.5,
          0.3499999940395355,
          0.0
        ],
        "chin": [
          0.5,
          0.41999998688697815,
          0.0
        ],
        "left_shoulder": [
          0.3799999952316284,
          0.6200000047683716,
          0.0
        ],
        "right_shoulder": [
          0.6200000047683716,
          0.6200000047683716,
          0.0
        ],
        "shoulder_center": [
          0.5,
          0.6200000047683716,
          0.0
        ],
        "nose": [
          0.5,
          0.3100000023841858,
          0.0
        ],
        "scale_hint": 0.24
      }
    },
    {
      "handedness": "right",
      "hand_landmarks": [
        [
          0.48241379857063293,
          0.4244827628135681,
          0.0
        ],
        [
          0.4892137944698334,
          0.4227827489376068,
          0.0
        ],
        [
          0.4926137924194336,
          0.4193827509880066,
          0.0
        ],
        [
          0.4960137903690338,
          0.41598275303840637,
          0.0
        ],
        [
          0.501113772392273,
          0.41428276896476746,
          0.0
        ],
        [
          0.48751381039619446,
          0.407482773065567,
          0.0
        ],
        [
          0.48751381039619446,
          0.3870827555656433,
          0.0
        ],
        [
          0.48751381039619446,
          0.3632827699184418,
          0.0
        ],
        [
          0.48751381039619446,
          0.3360827565193176,
          0.0
        ],
        [
          0.48241379857063293,
          0.41088277101516724,
          0.0
        ],
        [
          0.48241379857063293,
          0.4040827751159668,
          0.0
        ],
        [
          0.48241379857063293,
          0.3989827632904053,
          0.0
        ],
        [
          0.48241379857063293,
          0.39728274941444397,
          0.0
        ],
        [
          0.4773137867450714,
          0.41088277101516724,
          0.0
        ],
        [
          0.4773137867450714,
          0.4057827591896057,
          0.0
        ],
        [
          0.4773137867450714,
          0.4023827612400055,
          0.0
        ],
        [
          0.4773137867450714,
          0.4006827473640442,
          0.0
        ],
        [
          0.4722138047218323,
          0.41258275508880615,
          0.0
        ],
        [
          0.4722138047218323,
          0.407482773065567,
          0.0
        ],
        [
          0.4722138047218323,
          0.4040827751159668,
          0.0
        ],
        [
          0.4722138047218323,
          0.4023827612400055,
          0.0
        ]
      ],
      "hand_center": [
        0.4828185439109802,
        0.4023018479347229,
        0.0
      ],
      "openness": 2.3032357692718506,
      "palm_size": 0.01612761616706848,
      "scale_hint": 0.24,
      "anchors": {
        "forehead": [
          0.5,
          0.23999999463558197,
          0.0
        ],
        "mouth": [
          0.5,
          0.3499999940395355,
          0.0
        ],
        "chin": [
          0.5,
          0.41999998688697815,
          0.0
        ],
        "left_shoulder": [
          0.3799999952316284,
          0.6200000047683716,
          0.0
        ],
        "right_shoulder": [
          0.6200000047683716,
          0.6200000047683716,
          0.0
        ],
        "shoulder_center": [
          0.5,
          0.6200000047683716,
          0.0
        ],
        "nose": [
          0.5,
          0.3100000023841858,
          0.0
        ],
        "scale_hint": 0.24
      }
    },
    {
      "handedness": "right",
      "hand_landmarks": [
        [
          0.4831034541130066,
          0.42862069606781006,
          0.0
        ],
        [
          0.48990345001220703,
          0.42692068219184875,
          0.0
        ],
        [
          0.49330344796180725,
          0.42352068424224854,
          0.0
        ],
        [
          0.49670344591140747,
          0.4201206862926483,
          0.0
        ],
        [
          0.501803457736969,
          0.4184207022190094,
          0.0
        ],
        [
          0.4882034659385681,
          0.41162070631980896,
          0.0
        ],
        [
          0.4882034659385681,
          0.39122068881988525,
          0.0
        ],
        [
          0.4882034659385681,
          0.3674207031726837,
          0.0
        ],
        [
          0.4882034659385681,
          0.34022068977355957,
          0.0
        ],
        [
          0.4831034541130066,
          0.4150207042694092,
          0.0
        ],
        [
          0.4831034541130066,
          0.40822070837020874,
          0.0
        ],
        [
          0.4831034541130066,
          0.4031206965446472,
          0.0
        ],
        [
          0.4831034541130066,
          0.4014206826686859,
          0.0
        ],
        [
          0.47800344228744507,
          0.4150207042694092,
          0.0
        ],
        [
          0.47800344228744507,
          0.40992069244384766,
          0.0
        ],
        [
          0.47800344228744507,
          0.40652069449424744,
          0.0
        ],
        [
          0.47800344228744507,
          0.40482068061828613,
          0.0
        ],
        [
          0.47290346026420593,
          0.4167206883430481,
          0.0
        ],
        [
          0.47290346026420593,
          0.41162070631980896,
          0.0
        ],
        [
          0.47290346026420593,
          0.40822070837020874,
          0.0
        ],
        [
          0.47290346026420593,
          0.40652069449424744,
          0.0
        ]
      ],
      "hand_center": [
        0.4835081696510315,
        0.40643972158432007,
        0.0
      ],
      "openness": 2.303236246109009,
      "palm_size": 0.01612761616706848,
      "scale_hint": 0.24,
      "anchors": {
        "forehead": [
          0.5,
          0.23999999463558197,
          0.0
        ],
        "mouth": [
          0.5,
          0.3499999940395355,
          0.0
        ],
        "chin": [
          0.5,
          0.41999998688697815,
          0.0
        ],
        "left_shoulder": [
          0.3799999952316284,
          0.6200000047683716,
          0.0
        ],
        "right_shoulder": [
          0.6200000047683716,
          0.6200000047683716,
          0.0
        ],
        "shoulder_center": [
          0.5,
          0.6200000047683716,
          0.0
        ],
        "nose": [
          0.5,
          0.3100000023841858,
          0.0
        ],
        "scale_hint": 0.24
      }
    },
    {
      "handedness": "right",
      "hand_landmarks": [
        [
          0.48379310965538025,
          0.432758629322052,
          0.0
        ],
        [
          0.4905931055545807,
          0.4310586154460907,
          0.0
        ],
        [
          0.4939931035041809,
          0.4276586174964905,
          0.0
        ],
        [
          0.49739310145378113,
          0.42425861954689026,
          0.0
        ],
        [
          0.5024930834770203,
          0.42255863547325134,
          0.0
        ],
        [
          0.4888931214809418,
          0.4157586395740509,
          0.0
        ],
        [
          0.4888931214809418,
          0.3953586220741272,
          0.0
        ],
        [
          0.4888931214809418,
          0.37155863642692566,
          0.0
        ],
        [
          0.4888931214809418,
          0.3443586230278015,
          0.0
        ],
        [
          0.48379310965538025,
          0.4191586375236511,
          0.0
        ],
        [
          0.48379310965538025,
          0.4123586416244507,
          0.0
        ],
        [
          0.48379310965538025,
          0.40725862979888916,
          0.0
        ],
        [
          0.48379310965538025,
          0.40555861592292786,
          0.0
        ],
        [
          0.4786930978298187,
          0.4191586375236511,
          0.0
        ],
        [
          0.4786930978298187,
          0.4140586256980896,
          0.0
        ],
        [
          0.4786930978298187,
          0.4106586277484894,
          0.0
        ],
        [
          0.4786930978298187,
          0.4089586138725281,
          0.0
        ],
        [
          0.4735931158065796,
          0.42085862159729004,
          0.0
        ],
        [
          0.4735931158065796,
          0.4157586395740509,
          0.0
        ],
        [
          0.4735931158065796,
          0.4123586416244507,
          0.0
        ],
        [
          0.4735931158065796,
          0.4106586277484894,
          0.0
        ]
      ],
      "hand_center": [
        0.48419779539108276,
        0.4105776846408844,
        0.0
      ],
      "openness": 2.3032357692718506,
      "palm_size": 0.01612761616706848,
      "scale_hint": 0.24,
      "anchors": {
        "forehead": [
          0.5,
          0.23999999463558197,
          0.0
        ],
        "mouth": [
          0.5,
          0.3499999940395355,
          0.0
        ],
        "chin": [
          0.5,
          0.41999998688697815,
          0.0
        ],
        "left_shoulder": [
          0.3799999952316284,
          0.6200000047683716,
          0.0
        ],
        "right_shoulder": [
          0.6200000047683716,
          0.6200000047683716,
          0.0
        ],
        "shoulder_center": [
          0.5,
          0.6200000047683716,
          0.0
        ],
        "nose": [
          0.5,
          0.3100000023841858,
          0.0
        ],
        "scale_hint": 0.24
      }
    },
    {
      "handedness": "right",
      "hand_landmarks": [
        [
          0.4844827651977539,
          0.43689653277397156,
          0.0
        ],
        [
          0.49128276109695435,
          0.43519651889801025,
          0.0
        ],
        [
          0.49468275904655457,
          0.43179652094841003,
          0.0
        ],
        [
          0.4980827569961548,
          0.4283965229988098,
          0.0
        ],
        [
          0.5031827688217163,
          0.4266965389251709,
          0.0
        ],
        [
          0.48958277702331543,
          0.41989654302597046,
          0.0
        ],
        [
          0.48958277702331543,
          0.39949652552604675,
          0.0
        ],
        [
          0.48958277702331543,
          0.3756965398788452,
          0.0
        ],
        [
          0.48958277702331543,
          0.34849652647972107,
          0.0
        ],
        [
          0.4844827651977539,
          0.4232965409755707,
          0.0
        ],
        [
          0.4844827651977539,
          0.41649654507637024,
          0.0
        ],
        [
          0.4844827651977539,
          0.4113965332508087,
          0.0
        ],
        [
          0.4844827651977539,
          0.4096965193748474,
          0.0
        ],
        [
          0.4793827533721924,
          0.4232965409755707,
          0.0
        ],
        [
          0.4793827533721924,
          0.41819652915000916,
          0.0
        ],
        [
          0.4793827533721924,
          0.41479653120040894,
          0.0
        ],
        [
          0.4793827533721924,
          0.41309654712677,
          0.0
        ],
        [
          0.47428277134895325,
          0.4249965250492096,
          0.0
        ],
        [
          0.47428277134895325,
          0.41989654302597046,
          0.0
        ],
        [
          0.47428277134895325,
          0.41649654507637024,
          0.0
        ],
        [
          0.47428277134895325,
          0.41479653120040894,
          0.0
        ]
      ],
      "hand_center": [
        0.48488757014274597,
        0.41471558809280396,
        0.0
      ],
      "openness": 2.3032357692718506,
      "palm_size": 0.01612761616706848,
      "scale_hint": 0.24,
      "anchors": {
        "forehead": [
          0.5,
          0.23999999463558197,
          0.0
        ],
        "mouth": [
          0.5,
          0.3499999940395355,
          0.0
        ],
        "chin": [
          0.5,
          0.41999998688697815,
          0.0
        ],
        "left_shoulder": [
          0.3799999952316284,
          0.6200000047683716,
          0.0
        ],
        "right_shoulder": [
          0.6200000047683716,
          0.6200000047683716,
          0.0
        ],
        "shoulder_center": [
          0.5,
          0.6200000047683716,
          0.0
        ],
        "nose": [
          0.5,
          0.3100000023841858,
          0.0
        ],
        "scale_hint": 0.24
      }
    },
    {
      "handedness": "right",
      "hand_landmarks": [
        [
          0.48517242074012756,
          0.4410344660282135,
          0.0
        ],
        [
          0.491972416639328,
          0.4393344521522522,
          0.0
        ],
        [
          0.4953724145889282,
          0.435934454202652,
          0.0
        ],
        [
          0.49877241253852844,
          0.43253445625305176,
          0.0
        ],
        [
          0.5038723945617676,
          0.43083447217941284,
          0.0
        ],
        [
          0.4902724325656891,
          0.4240344762802124,
          0.0
        ],
        [
          0.4902724325656891,
          0.4036344587802887,
          0.0
        ],
        [
          0.4902724325656891,
          0.37983447313308716,
          0.0
        ],
        [
          0.4902724325656891,
          0.352634459733963,
          0.0
        ],
        [
          0.48517242074012756,
          0.4274344742298126,
          0.0
        ],
        [
          0.48517242074012756,
          0.4206344783306122,
          0.0
        ],
        [
          0.48517242074012756,
          0.41553446650505066,
          0.0
        ],
        [
          0.48517242074012756,
          0.41383445262908936,
          0.0
        ],
        [
          0.48007240891456604,
          0.4274344742298126,
          0.0
        ],
        [
          0.48007240891456604,
          0.4223344624042511,
          0.0
        ],
        [
          0.48007240891456604,
          0.4189344644546509,
          0.0
        ],
        [
          0.48007240891456604,
          0.41723448038101196,
          0.0
        ],
        [
          0.4749724268913269,
          0.42913445830345154,
          0.0
        ],
        [
          0.4749724268913269,
          0.4240344762802124,
          0.0
        ],
        [
          0.4749724268913269,
          0.4206344783306122,
          0.0
        ],
        [
          0.4749724268913269,
          0.4189344644546509,
          0.0
        ]
      ],
      "hand_center": [
        0.48557722568511963,
        0.4188535213470459,
        0.0
      ],
      "openness": 2.3032352924346924,
      "palm_size": 0.01612761616706848,
      "scale_hint": 0.24,
      "anchors": {
        "forehead": [
          0.5,
          0.23999999463558197,
          0.0
        ],
        "mouth": [
          0.5,
          0.3499999940395355,
          0.0
        ],
        "chin": [
          0.5,
          0.41999998688697815,
          0.0
        ],
        "left_shoulder": [
          0.3799999952316284,
          0.6200000047683716,
          0.0
        ],
        "right_shoulder": [
          0.6200000047683716,
          0.6200000047683716,
          0.0
        ],
        "shoulder_center": [
          0.5,
          0.6200000047683716,
          0.0
        ],
        "nose": [
          0.5,
          0.3100000023841858,
          0.0
        ],
        "scale_hint": 0.24
      }
    },
    {
      "handedness": "right",
      "hand_landmarks": [
        [
          0.4858620762825012,
          0.44517239928245544,
          0.0
        ],
        [
          0.49266207218170166,
          0.44347238540649414,
          0.0
        ],
        [
          0.4960620701313019,
          0.4400723874568939,
          0.0
        ],
        [
          0.4994620680809021,
          0.4366723895072937,
          0.0
        ],
        [
          0.5045620799064636,
          0.4349724054336548,
          0.0
        ],
        [
          0.49096208810806274,
          0.42817240953445435,
          0.0
        ],
        [
          0.49096208810806274,
          0.40777239203453064,
          0.0
        ],
        [
          0.49096208810806274,
          0.3839724063873291,
          0.0
        ],
        [
          0.49096208810806274,
          0.35677239298820496,
          0.0
        ],
        [
          0.4858620762825012,
          0.43157240748405457,
          0.0
        ],
        [
          0.4858620762825012,
          0.4247724115848541,
          0.0
        ],
        [
          0.4858620762825012,
          0.4196723997592926,
          0.0
        ],
        [
          0.4858620762825012,
          0.4179723858833313,
          0.0
        ],
        [
          0.4807620644569397,
          0.43157240748405457,
          0.0
        ],
        [
          0.4807620644569397,
          0.42647239565849304,
          0.0
        ],
        [
          0.4807620644569397,
          0.4230723977088928,
          0.0
        ],
        [
          0.4807620644569397,
          0.4213724136352539,
          0.0
        ],
        [
          0.47566208243370056,
          0.4332723915576935,
          0.0
        ],
        [
          0.47566208243370056,
          0.42817240953445435,
          0.0
        ],
        [
          0.47566208243370056,
          0.4247724115848541,
          0.0
        ],
        [
          0.47566208243370056,
          0.4230723977088928,
          0.0
        ]
      ],
      "hand_center": [
        0.4862669110298157,
        0.42299142479896545,
        0.0
      ],
      "openness": 2.3032357692718506,
      "palm_size": 0.01612761616706848,
      "scale_hint": 0.24,
      "anchors": {
        "forehead": [
          0.5,
          0.23999999463558197,
          0.0
        ],
        "mouth": [
          0.5,
          0.3499999940395355,
          0.0
        ],
        "chin": [
          0.5,
          0.41999998688697815,
          0.0
        ],
        "left_shoulder": [
          0.3799999952316284,
          0.6200000047683716,
          0.0
        ],
        "right_shoulder": [
          0.6200000047683716,
          0.6200000047683716,
          0.0
        ],
        "shoulder_center": [
          0.5,
          0.6200000047683716,
          0.0
        ],
        "nose": [
          0.5,
          0.3100000023841858,
          0.0
        ],
        "scale_hint": 0.24
      }
    },
    {
      "handedness": "right",
      "hand_landmarks": [
        [
          0.4865517318248749,
          0.4493103325366974,
          0.0
        ],
        [
          0.4933517277240753,
          0.4476103186607361,
          0.0
        ],
        [
          0.49675172567367554,
          0.44421032071113586,
          0.0
        ],
        [
          0.5001517534255981,
          0.44081032276153564,
          0.0
        ],
        [
          0.5052517056465149,
          0.43911033868789673,
          0.0
        ],
        [
          0.4916517436504364,
          0.4323103427886963,
          0.0
        ],
        [
          0.4916517436504364,
          0.4119103252887726,
          0.0
        ],
        [
          0.4916517436504364,
          0.38811033964157104,
          0.0
        ],
        [
          0.4916517436504364,
          0.3609103262424469,
          0.0
        ],
        [
          0.4865517318248749,
          0.4357103407382965,
          0.0
        ],
        [
          0.4865517318248749,
          0.42891034483909607,
          0.0
        ],
        [
          0.4865517318248749,
          0.42381033301353455,
          0.0
        ],
        [
          0.4865517318248749,
          0.42211031913757324,
          0.0
        ],
        [
          0.48145171999931335,
          0.4357103407382965,
          0.0
        ],
        [
          0.48145171999931335,
          0.430610328912735,
          0.0
        ],
        [
          0.48145171999931335,
          0.42721033096313477,
          0.0
        ],
        [
          0.48145171999931335,
          0.42551034688949585,
          0.0
        ],
        [
          0.4763517379760742,
          0.4374103248119354,
          0.0
        ],
        [
          0.4763517379760742,
          0.4323103427886963,
          0.0
        ],
        [
          0.4763517379760742,
          0.42891034483909607,
          0.0
        ],
        [
          0.4763517379760742,
          0.42721033096313477,
          0.0
        ]
      ],
      "hand_center": [
        0.4869564473628998,
        0.4271293878555298,
        0.0
      ],
      "openness": 2.3032352924346924,
      "palm_size": 0.01612761616706848,
      "scale_hint": 0.24,
      "anchors": {
        "forehead": [
          0.5,
          0.23999999463558197,
          0.0
        ],
        "mouth": [
          0.5,
          0.3499999940395355,
          0.0
        ],
        "chin": [
          0.5,
          0.41999998688697815,
          0.0
        ],
        "left_shoulder": [
          0.3799999952316284,
          0.6200000047683716,
          0.0
        ],
        "right_shoulder": [
          0.6200000047683716,
          0.6200000047683716,
          0.0
        ],
        "shoulder_center": [
          0.5,
          0.6200000047683716,
          0.0
        ],
        "nose": [
          0.5,
          0.3100000023841858,
          0.0
        ],
        "scale_hint": 0.24
      }
    },
    {
      "handedness": "right",
      "hand_landmarks": [
        [
          0.48724138736724854,
          0.45344826579093933,
          0.0
        ],
        [
          0.494041383266449,
          0.451748251914978,
          0.0
        ],
        [
          0.4974413812160492,
          0.4483482539653778,
          0.0
        ],
        [
          0.5008413791656494,
          0.4449482560157776,
          0.0
        ],
        [
          0.5059413909912109,
          0.44324827194213867,
          0.0
        ],
        [
          0.49234139919281006,
          0.43644827604293823,
          0.0
        ],
        [
          0.49234139919281006,
          0.4160482585430145,
          0.0
        ],
        [
          0.49234139919281006,
          0.392248272895813,
          0.0
        ],
        [
          0.49234139919281006,
          0.36504825949668884,
          0.0
        ],
        [
          0.48724138736724854,
          0.43984827399253845,
          0.0
        ],
        [
          0.48724138736724854,
          0.433048278093338,
          0.0
        ],
        [
          0.48724138736724854,
          0.4279482662677765,
          0.0
        ],
        [
          0.48724138736724854,
          0.4262482523918152,
          0.0
        ],
        [
          0.482141375541687,
          0.43984827399253845,
          0.0
        ],
        [
          0.482141375541687,
          0.43474826216697693,
          0.0
        ],
        [
          0.482141375541687,
          0.4313482642173767,
          0.0
        ],
        [
          0.482141375541687,
          0.4296482801437378,
          0.0
        ],
        [
          0.4770413935184479,
          0.44154825806617737,
          0.0
        ],
        [
          0.4770413935184479,
          0.43644827604293823,
          0.0
        ],
        [
          0.4770413935184479,
          0.433048278093338,
          0.0
        ],
        [
          0.4770413935184479,
          0.4313482642173767,
          0.0
        ]
      ],
      "hand_center": [
        0.4876461625099182,
        0.43126732110977173,
        0.0
      ],
      "openness": 2.3032357692718506,
      "palm_size": 0.01612761616706848,
      "scale_hint": 0.24,
      "anchors": {
        "forehead": [
          0.5,
          0.23999999463558197,
          0.0
        ],
        "mouth": [
          0.5,
          0.3499999940395355,
          0.0
        ],
        "chin": [
          0.5,
          0.41999998688697815,
          0.0
        ],
        "left_shoulder": [
          0.3799999952316284,
          0.6200000047683716,
          0.0
        ],
        "right_shoulder": [
          0.6200000047683716,
          0.6200000047683716,
          0.0
        ],
        "shoulder_center": [
          0.5,
          0.6200000047683716,
          0.0
        ],
        "nose": [
          0.5,
          0.3100000023841858,
          0.0
        ],
        "scale_hint": 0.24
      }
    },
    {
      "handedness": "right",
      "hand_landmarks": [
        [
          0.4879310429096222,
          0.4575861990451813,
          0.0
        ],
        [
          0.49473103880882263,
          0.45588618516921997,
          0.0
        ],
        [
          0.49813103675842285,
          0.45248618721961975,
          0.0
        ],
        [
          0.5015310645103455,
          0.44908618927001953,
          0.0
        ],
        [
          0.5066310167312622,
          0.4473862051963806,
          0.0
        ],
        [
          0.4930310547351837,
          0.4405862092971802,
          0.0
        ],
        [
          0.4930310547351837,
          0.42018619179725647,
          0.0
        ],
        [
          0.4930310547351837,
          0.39638620615005493,
          0.0
        ],
        [
          0.4930310547351837,
          0.3691861927509308,
          0.0
        ],
        [
          0.4879310429096222,
          0.4439862072467804,
          0.0
        ],
        [
          0.4879310429096222,
          0.43718621134757996,
          0.0
        ],
        [
          0.4879310429096222,
          0.43208619952201843,
          0.0
        ],
        [
          0.4879310429096222,
          0.43038618564605713,
          0.0
        ],
        [
          0.48283103108406067,
          0.4439862072467804,
          0.0
        ],
        [
          0.48283103108406067,
          0.43888619542121887,
          0.0
        ],
        [
          0.48283103108406067,
          0.43548619747161865,
          0.0
        ],
        [
          0.48283103108406067,
          0.43378621339797974,
          0.0
        ],
        [
          0.47773104906082153,
          0.4456861913204193,
          0.0
        ],
        [
          0.47773104906082153,
          0.4405862092971802,
          0.0
        ],
        [
          0.47773104906082153,
          0.43718621134757996,
          0.0
        ],
        [
          0.47773104906082153,
          0.43548619747161865,
          0.0
        ]
      ],
      "hand_center": [
        0.4883357882499695,
        0.43540528416633606,
        0.0
      ],
      "openness": 2.3032352924346924,
      "palm_size": 0.01612761616706848,
      "scale_hint": 0.24,
      "anchors": {
        "forehead": [
          0.5,
          0.23999999463558197,
          0.0
        ],
        "mouth": [
          0.5,
          0.3499999940395355,
          0.0
        ],
        "chin": [
          0.5,
          0.41999998688697815,
          0.0
        ],
        "left_shoulder": [
          0.3799999952316284,
          0.6200000047683716,
          0.0
        ],
        "right_shoulder": [
          0.6200000047683716,
          0.6200000047683716,
          0.0
        ],
        "shoulder_center": [
          0.5,
          0.6200000047683716,
          0.0
        ],
        "nose": [
          0.5,
          0.3100000023841858,
          0.0
        ],
        "scale_hint": 0.24
      }
    },
    {
      "handedness": "right",
      "hand_landmarks": [
        [
          0.48862069845199585,
          0.4617241322994232,
          0.0
        ],
        [
          0.4954206943511963,
          0.4600241184234619,
          0.0
        ],
        [
          0.4988206923007965,
          0.4566241204738617,
          0.0
        ],
        [
          0.5022206902503967,
          0.4532241225242615,
          0.0
        ],
        [
          0.5073207020759583,
          0.45152413845062256,
          0.0
        ],
        [
          0.4937207102775574,
          0.4447241425514221,
          0.0
        ],
        [
          0.4937207102775574,
          0.4243241250514984,
          0.0
        ],
        [
          0.4937207102775574,
          0.4005241394042969,
          0.0
        ],
        [
          0.4937207102775574,
          0.37332412600517273,
          0.0
        ],
        [
          0.48862069845199585,
          0.44812414050102234,
          0.0
        ],
        [
          0.48862069845199585,
          0.4413241446018219,
          0.0
        ],
        [
          0.48862069845199585,
          0.4362241327762604,
          0.0
        ],
        [
          0.48862069845199585,
          0.4345241189002991,
          0.0
        ],
        [
          0.4835206866264343,
          0.44812414050102234,
          0.0
        ],
        [
          0.4835206866264343,
          0.4430241286754608,
          0.0
        ],
        [
          0.4835206866264343,
          0.4396241307258606,
          0.0
        ],
        [
          0.4835206866264343,
          0.4379241466522217,
          0.0
        ],
        [
          0.4784207046031952,
          0.44982412457466125,
          0.0
        ],
        [
          0.4784207046031952,
          0.4447241425514221,
          0.0
        ],
        [
          0.4784207046031952,
          0.4413241446018219,
          0.0
        ],
        [
          0.4784207046031952,
          0.4396241307258606,
          0.0
        ]
      ],
      "hand_center": [
        0.48902538418769836,
        0.4395431876182556,
        0.0
      ],
      "openness": 2.3032357692718506,
      "palm_size": 0.01612761616706848,
      "scale_hint": 0.24,
      "anchors": {
        "forehead": [
          0.5,
          0.23999999463558197,
          0.0
        ],
        "mouth": [
          0.5,
          0.3499999940395355,
          0.0
        ],
        "chin": [
          0.5,
          0.41999998688697815,
          0.0
        ],
        "left_shoulder": [
          0.3799999952316284,
          0.6200000047683716,
          0.0
        ],
        "right_shoulder": [
          0.6200000047683716,
          0.6200000047683716,
          0.0
        ],
        "shoulder_center": [
          0.5,
          0.6200000047683716,
          0.0
        ],
        "nose": [
          0.5,
          0.3100000023841858,
          0.0
        ],
        "scale_hint": 0.24
      }
    },
    {
      "handedness": "right",
      "hand_landmarks": [
        [
          0.4893103539943695,
          0.46586206555366516,
          0.0
        ],
        [
          0.49611034989356995,
          0.46416205167770386,
          0.0
        ],
        [
          0.49951034784317017,
          0.46076205372810364,
          0.0
        ],
        [
          0.5029103755950928,
          0.4573620557785034,
          0.0
        ],
        [
          0.5080103278160095,
          0.4556620717048645,
          0.0
        ],
        [
          0.49441036581993103,
          0.44886207580566406,
          0.0
        ],
        [
          0.49441036581993103,
          0.42846205830574036,
          0.0
        ],
        [
          0.49441036581993103,
          0.4046620726585388,
          0.0
        ],
        [
          0.49441036581993103,
          0.3774620592594147,
          0.0
        ],
        [
          0.4893103539943695,
          0.4522620737552643,
          0.0
        ],
        [
          0.4893103539943695,
          0.44546207785606384,
          0.0
        ],
        [
          0.4893103539943695,
          0.4403620660305023,
          0.0
        ],
        [
          0.4893103539943695,
          0.438662052154541,
          0.0
        ],
        [
          0.484210342168808,
          0.4522620737552643,
          0.0
        ],
        [
          0.484210342168808,
          0.44716206192970276,
          0.0
        ],
        [
          0.484210342168808,
          0.44376206398010254,
          0.0
        ],
        [
          0.484210342168808,
          0.4420620799064636,
          0.0
        ],
        [
          0.47911036014556885,
          0.4539620578289032,
          0.0
        ],
        [
          0.47911036014556885,
          0.44886207580566406,
          0.0
        ],
        [
          0.47911036014556885,
          0.44546207785606384,
          0.0
        ],
        [
          0.47911036014556885,
          0.44376206398010254,
          0.0
        ]
      ],
      "hand_center": [
        0.4897151589393616,
        0.44368109107017517,
        0.0
      ],
      "openness": 2.3032352924346924,
      "palm_size": 0.01612761616706848,
      "scale_hint": 0.24,
      "anchors": {
        "forehead": [
          0.5,
          0.23999999463558197,
          0.0
        ],
        "mouth": [
          0.5,
          0.3499999940395355,
          0.0
        ],
        "chin": [
          0.5,
          0.41999998688697815,
          0.0
        ],
        "left_shoulder": [
          0.3799999952316284,
          0.6200000047683716,
          0.0
        ],
        "right_shoulder": [
          0.6200000047683716,
          0.6200000047683716,
          0.0
        ],
        "shoulder_center": [
          0.5,
          0.6200000047683716,
          0.0
        ],
        "nose": [
          0.5,
          0.3100000023841858,
          0.0
        ],
        "scale_hint": 0.24
      }
    },
    {
      "handedness": "right",
      "hand_landmarks": [
        [
          0.49000000953674316,
          0.4699999988079071,
          0.0
        ],
        [
          0.4968000054359436,
          0.4682999849319458,
          0.0
        ],
        [
          0.5002000331878662,
          0.4648999869823456,
          0.0
        ],
        [
          0.503600001335144,
          0.46149998903274536,
          0.0
        ],
        [
          0.5087000131607056,
          0.45980000495910645,
          0.0
        ],
        [
          0.4951000213623047,
          0.453000009059906,
          0.0
        ],
        [
          0.4951000213623047,
          0.4325999915599823,
          0.0
        ],
        [
          0.4951000213623047,
          0.40880000591278076,
          0.0
        ],
        [
          0.4951000213623047,
          0.3815999925136566,
          0.0
        ],
        [
          0.49000000953674316,
          0.4564000070095062,
          0.0
        ],
        [
          0.49000000953674316,
          0.4496000111103058,
          0.0
        ],
        [
          0.49000000953674316,
          0.44449999928474426,
          0.0
        ],
        [
          0.49000000953674316,
          0.44279998540878296,
          0.0
        ],
        [
          0.48489999771118164,
          0.4564000070095062,
          0.0
        ],
        [
          0.48489999771118164,
          0.4512999951839447,
          0.0
        ],
        [
          0.48489999771118164,
          0.4478999972343445,
          0.0
        ],
        [
          0.48489999771118164,
          0.44620001316070557,
          0.0
        ],
        [
          0.4798000156879425,
          0.45809999108314514,
          0.0
        ],
        [
          0.4798000156879425,
          0.453000009059906,
          0.0
        ],
        [
          0.4798000156879425,
          0.4496000111103058,
          0.0
        ],
        [
          0.4798000156879425,
          0.4478999972343445,
          0.0
        ]
      ],
      "hand_center": [
        0.49040475487709045,
        0.4478190839290619,
        0.0
      ],
      "openness": 2.3032357692718506,
      "palm_size": 0.01612761616706848,
      "scale_hint": 0.24,
      "anchors": {
        "forehead": [
          0.5,
          0.23999999463558197,
          0.0
        ],
        "mouth": [
          0.5,
          0.3499999940395355,
          0.0
        ],
        "chin": [
          0.5,
          0.41999998688697815,
          0.0
        ],
        "left_shoulder": [
          0.3799999952316284,
          0.6200000047683716,
          0.0
        ],
        "right_shoulder": [
          0.6200000047683716,
          0.6200000047683716,
          0.0
        ],
        "shoulder_center": [
          0.5,
          0.6200000047683716,
          0.0
        ],
        "nose": [
          0.5,
          0.3100000023841858,
          0.0
        ],
        "scale_hint": 0.24
      }
    }
  ]
}