{
  "sequence_version": 1,
  "exercise": "where",
  "source": "synthetic_default",
  "profile": {
    "label": "where",
    "anchor": "mouth",
    "hand_shape": "index_point",
    "path": "question_shake",
    "hand_scale": 0.17
  },
  "frame_count_original": 30,
  "usable_frame_count": 30,
  "resampled_frame_count": 30,
  "handedness": "right",
  "frames": [
    {
      "handedness": "right",
      "hand_landmarks": [
        [
          0.550000011920929,
          0.3799999952316284,
          0.0
        ],
        [
          0.5568000078201294,
          0.3782999813556671,
          0.0
        ],
        [
          0.560200035572052,
          0.3748999834060669,
          0.0
        ],
        [
          0.5636000037193298,
          0.3714999854564667,
          0.0
        ],
        [
          0.5687000155448914,
          0.36980000138282776,
          0.0
        ],
        [
          0.5551000237464905,
          0.3630000054836273,
          0.0
        ],
        [
          0.5551000237464905,
          0.3425999879837036,
          0.0
        ],
        [
          0.5551000237464905,
          0.3188000023365021,
          0.0
        ],
        [
          0.5551000237464905,
          0.29159998893737793,
          0.0
        ],
        [
          0.550000011920929,
          0.36640000343322754,
          0.0
        ],
        [
          0.550000011920929,
          0.3596000075340271,
          0.0
        ],
        [
          0.550000011920929,
          0.3544999957084656,
          0.0
        ],
        [
          0.550000011920929,
          0.3527999818325043,
          0.0
        ],
        [
          0.5449000000953674,
          0.36640000343322754,
          0.0
        ],
        [
          0.5449000000953674,
          0.361299991607666,
          0.0
        ],
        [
          0.5449000000953674,
          0.3578999936580658,
          0.0
        ],
        [
          0.5449000000953674,
          0.3561999797821045,
          0.0
        ],
        [
          0.5397999882698059,
          0.36809998750686646,
          0.0
        ],
        [
          0.5397999882698059,
          0.3630000054836273,
          0.0
        ],
        [
          0.5397999882698059,
          0.3596000075340271,
          0.0
        ],
        [
          0.5397999882698059,
          0.3578999936580658,
          0.0
        ]
      ],
      "hand_center": [
        0.5504047274589539,
        0.3578190803527832,
        0.0
      ],
      "openness": 2.303232431411743,
      "palm_size": 0.01612764410674572,
      "scale_hint": 0.24,
      "anchors": {
        "forehead": [
          0.5,
          0.23999999463558197,
          0.0
        ],
        "mouth": [
          0.5,
          0.3499999940395355,
          0.0
        ],
        "chin": [
          0.5,
          0.41999998688697815,
          0.0
        ],
        "left_shoulder": [
          0.3799999952316284,
          0.6200000047683716,
          0.0
        ],
        "right_shoulder": [
          0.6200000047683716,
          0.6200000047683716,
          0.0
        ],
        "shoulder_center": [
          0.5,
          0.6200000047683716,
          0.0
        ],
        "nose": [
          0.5,
          0.3100000023841858,
          0.0
        ],
        "scale_hint": 0.24
      }
    },
    {
      "handedness": "right",
      "hand_landmarks": [
        [
          0.57099449634552,
          0.3799999952316284,
          0.0
        ],
        [
          0.5777944922447205,
          0.3782999813556671,
          0.0
        ],
        [
          0.5811945199966431,
          0.3748999834060669,
          0.0
        ],
        [
          0.5845944881439209,
          0.3714999854564667,
          0.0
        ],
        [
          0.5896944999694824,
          0.36980000138282776,
          0.0
        ],
        [
          0.5760945081710815,
          0.3630000054836273,
          0.0
        ],
        [
          0.5760945081710815,
          0.3425999879837036,
          0.0
        ],
        [
          0.5760945081710815,
          0.3188000023365021,
          0.0
        ],
        [
          0.5760945081710815,
          0.29159998893737793,
          0.0
        ],
        [
          0.57099449634552,
          0.36640000343322754,
          0.0
        ],
        [
          0.57099449634552,
          0.3596000075340271,
          0.0
        ],
        [
          0.57099449634552,
          0.3544999957084656,
          0.0
        ],
        [
          0.57099449634552,
          0.3527999818325043,
          0.0
        ],
        [
          0.5658944845199585,
          0.36640000343322754,
          0.0
        ],
        [
          0.5658944845199585,
          0.361299991607666,
          0.0
        ],
        [
          0.5658944845199585,
          0.3578999936580658,
          0.0
        ],
        [
          0.5658944845199585,
          0.3561999797821045,
          0.0
        ],
        [
          0.560794472694397,
          0.36809998750686646,
          0.0
        ],
        [
          0.560794472694397,
          0.3630000054836273,
          0.0
        ],
        [
          0.560794472694397,
          0.3596000075340271,
          0.0
        ],
        [
          0.560794472694397,
          0.3578999936580658,
          0.0
        ]
      ],
      "hand_center": [
        0.5713992714881897,
        0.3578190803527832,
        0.0
      ],
      "openness": 2.303232431411743,
      "palm_size": 0.01612764410674572,
      "scale_hint": 0.24,
      "anchors": {
        "forehead": [
          0.5,
          0.23999999463558197,
          0.0
        ],
        "mouth": [
          0.5,
          0.3499999940395355,
          0.0
        ],
        "chin": [
          0.5,
          0.41999998688697815,
          0.0
        ],
        "left_shoulder": [
          0.3799999952316284,
          0.6200000047683716,
          0.0
        ],
        "right_shoulder": [
          0.6200000047683716,
          0.6200000047683716,
          0.0
        ],
        "shoulder_center": [
          0.5,
          0.6200000047683716,
          0.0
        ],
        "nose": [
          0.5,
          0.3100000023841858,
          0.0
        ],
        "scale_hint": 0.24
      }
    },
    {
      "handedness": "right",
      "hand_landmarks": [
        [
          0.5881081223487854,
          0.3799999952316284,
          0.0
        ],
        [
          0.5949081182479858,
          0.3782999813556671,
          0.0
        ],
        [
          0.5983081459999084,
          0.3748999834060669,
          0.0
        ],
        [
          0.6017081141471863,
          0.3714999854564667,
          0.0
        ],
        [
          0.6068081259727478,
          0.36980000138282776,
          0.0
        ],
        [
          0.5932081341743469,
          0.3630000054836273,
          0.0
        ],
        [
          0.5932081341743469,
          0.3425999879837036,
          0.0
        ],
        [
          0.5932081341743469,
          0.3188000023365021,
          0.0
        ],
        [
          0.5932081341743469,
          0.29159998893737793,
          0.0
        ],
        [
          0.5881081223487854,
          0.36640000343322754,
          0.0
        ],
        [
          0.5881081223487854,
          0.3596000075340271,
          0.0
        ],
        [
          0.5881081223487854,
          0.3544999957084656,
          0.0
        ],
        [
          0.5881081223487854,
          0.3527999818325043,
          0.0
        ],
        [
          0.5830081105232239,
          0.36640000343322754,
          0.0
        ],
        [
          0.5830081105232239,
          0.361299991607666,
          0.0
        ],
        [
          0.5830081105232239,
          0.3578999936580658,
          0.0
        ],
        [
          0.5830081105232239,
          0.3561999797821045,
          0.0
        ],
        [
          0.5779080986976624,
          0.36809998750686646,
          0.0
        ],
        [
          0.5779080986976624,
          0.3630000054836273,
          0.0
        ],
        [
          0.5779080986976624,
          0.3596000075340271,
          0.0
        ],
        [
          0.5779080986976624,
          0.3578999936580658,
          0.0
        ]
      ],
      "hand_center": [
        0.5885128974914551,
        0.3578190803527832,
        0.0
      ],
      "openness": 2.303232431411743,
      "palm_size": 0.01612764410674572,
      "scale_hint": 0.24,
      "anchors": {
        "forehead": [
          0.5,
          0.23999999463558197,
          0.0
        ],
        "mouth": [
          0.5,
          0.3499999940395355,
          0.0
        ],
        "chin": [
          0.5,
          0.41999998688697815,
          0.0
        ],
        "left_shoulder": [
          0.3799999952316284,
          0.6200000047683716,
          0.0
        ],
        "right_shoulder": [
          0.6200000047683716,
          0.6200000047683716,
          0.0
        ],
        "shoulder_center": [
          0.5,
          0.6200000047683716,
          0.0
        ],
        "nose": [
          0.5,
          0.3100000023841858,
          0.0
        ],
        "scale_hint": 0.24
      }
    },
    {
      "handedness": "right",
      "hand_landmarks": [
        [
          0.5981774926185608,
          0.3799999952316284,
          0.0
        ],
        [
          0.6049774885177612,
          0.3782999813556671,
          0.0
        ],
        [
          0.6083775162696838,
          0.3748999834060669,
          0.0
        ],
        [
          0.6117774844169617,
          0.3714999854564667,
          0.0
        ],
        [
          0.6168774962425232,
          0.36980000138282776,
          0.0
        ],
        [
          0.6032775044441223,
          0.3630000054836273,
          0.0
        ],
        [
          0.6032775044441223,
          0.3425999879837036,
          0.0
        ],
        [
          0.6032775044441223,
          0.3188000023365021,
          0.0
        ],
        [
          0.6032775044441223,
          0.29159998893737793,
          0.0
        ],
        [
          0.5981774926185608,
          0.36640000343322754,
          0.0
        ],
        [
          0.5981774926185608,
          0.3596000075340271,
          0.0
        ],
        [
          0.5981774926185608,
          0.3544999957084656,
          0.0
        ],
        [
          0.5981774926185608,
          0.3527999818325043,
          0.0
        ],
        [
          0.5930774807929993,
          0.36640000343322754,
          0.0
        ],
        [
          0.5930774807929993,
          0.361299991607666,
          0.0
        ],
        [
          0.5930774807929993,
          0.3578999936580658,
          0.0
        ],
        [
          0.5930774807929993,
          0.3561999797821045,
          0.0
        ],
        [
          0.5879774689674377,
          0.36809998750686646,
          0.0
        ],
        [
          0.5879774689674377,
          0.3630000054836273,
          0.0
        ],
        [
          0.5879774689674377,
          0.3596000075340271,
          0.0
        ],
        [
          0.5879774689674377,
          0.3578999936580658,
          0.0
        ]
      ],
      "hand_center": [
        0.5985822677612305,
        0.3578190803527832,
        0.0
      ],
      "openness": 2.303232431411743,
      "palm_size": 0.01612764410674572,
      "scale_hint": 0.24,
      "anchors": {
        "forehead": [
          0.5,
          0.23999999463558197,
          0.0
        ],
        "mouth": [
          0.5,
          0.3499999940395355,
          0.0
        ],
        "chin": [
          0.5,
          0.41999998688697815,
          0.0
        ],
        "left_shoulder": [
          0.3799999952316284,
          0.6200000047683716,
          0.0
        ],
        "right_shoulder": [
          0.6200000047683716,
          0.6200000047683716,
          0.0
        ],
        "shoulder_center": [
          0.5,
          0.6200000047683716,
          0.0
        ],
        "nose": [
          0.5,
          0.3100000023841858,
          0.0
        ],
        "scale_hint": 0.24
      }
    },
    {
      "handedness": "right",
      "hand_landmarks": [
        [
          0.5993413329124451,
          0.3799999952316284,
          0.0
        ],
        [
          0.6061413288116455,
          0.3782999813556671,
          0.0
        ],
        [
          0.6095413565635681,
          0.3748999834060669,
          0.0
        ],
        [
          0.612941324710846,
          0.3714999854564667,
          0.0
        ],
        [
          0.6180413365364075,
          0.36980000138282776,
          0.0
        ],
        [
          0.6044413447380066,
          0.3630000054836273,
          0.0
        ],
        [
          0.6044413447380066,
          0.3425999879837036,
          0.0
        ],
        [
          0.6044413447380066,
          0.3188000023365021,
          0.0
        ],
        [
          0.6044413447380066,
          0.29159998893737793,
          0.0
        ],
        [
          0.5993413329124451,
          0.36640000343322754,
          0.0
        ],
        [
          0.5993413329124451,
          0.3596000075340271,
          0.0
        ],
        [
          0.5993413329124451,
          0.3544999957084656,
          0.0
        ],
        [
          0.5993413329124451,
          0.3527999818325043,
          0.0
        ],
        [
          0.5942413210868835,
          0.36640000343322754,
          0.0
        ],
        [
          0.5942413210868835,
          0.361299991607666,
          0.0
        ],
        [
          0.5942413210868835,
          0.3578999936580658,
          0.0
        ],
        [
          0.5942413210868835,
          0.3561999797821045,
          0.0
        ],
        [
          0.589141309261322,
          0.36809998750686646,
          0.0
        ],
        [
          0.589141309261322,
          0.3630000054836273,
          0.0
        ],
        [
          0.589141309261322,
          0.3596000075340271,
          0.0
        ],
        [
          0.589141309261322,
          0.3578999936580658,
          0.0
        ]
      ],
      "hand_center": [
        0.5997459888458252,
        0.3578190803527832,
        0.0
      ],
      "openness": 2.303232431411743,
      "palm_size": 0.01612764410674572,
      "scale_hint": 0.24,
      "anchors": {
        "forehead": [
          0.5,
          0.23999999463558197,
          0.0
        ],
        "mouth": [
          0.5,
          0.3499999940395355,
          0.0
        ],
        "chin": [
          0.5,
          0.41999998688697815,
          0.0
        ],
        "left_shoulder": [
          0.3799999952316284,
          0.6200000047683716,
          0.0
        ],
        "right_shoulder": [
          0.6200000047683716,
          0.6200000047683716,
          0.0
        ],
        "shoulder_center": [
          0.5,
          0.6200000047683716,
          0.0
        ],
        "nose": [
          0.5,
          0.3100000023841858,
          0.0
        ],
        "scale_hint": 0.24
      }
    },
    {
      "handedness": "right",
      "hand_landmarks": [
        [
          0.5913844704627991,
          0.3799999952316284,
          0.0
        ],
        [
          0.5981844663619995,
          0.3782999813556671,
          0.0
        ],
        [
          0.6015844941139221,
          0.3748999834060669,
          0.0
        ],
        [
          0.6049844622612,
          0.3714999854564667,
          0.0
        ],
        [
          0.6100844740867615,
          0.36980000138282776,
          0.0
        ],
        [
          0.5964844822883606,
          0.3630000054836273,
          0.0
        ],
        [
          0.5964844822883606,
          0.3425999879837036,
          0.0
        ],
        [
          0.5964844822883606,
          0.3188000023365021,
          0.0
        ],
        [
          0.5964844822883606,
          0.29159998893737793,
          0.0
        ],
        [
          0.5913844704627991,
          0.36640000343322754,
          0.0
        ],
        [
          0.5913844704627991,
          0.3596000075340271,
          0.0
        ],
        [
          0.5913844704627991,
          0.3544999957084656,
          0.0
        ],
        [
          0.5913844704627991,
          0.3527999818325043,
          0.0
        ],
        [
          0.5862844586372375,
          0.36640000343322754,
          0.0
        ],
        [
          0.5862844586372375,
          0.361299991607666,
          0.0
        ],
        [
          0.5862844586372375,
          0.3578999936580658,
          0.0
        ],
        [
          0.5862844586372375,
          0.3561999797821045,
          0.0
        ],
        [
          0.581184446811676,
          0.36809998750686646,
          0.0
        ],
        [
          0.581184446811676,
          0.3630000054836273,
          0.0
        ],
        [
          0.581184446811676,
          0.3596000075340271,
          0.0
        ],
        [
          0.581184446811676,
          0.3578999936580658,
          0.0
        ]
      ],
      "hand_center": [
        0.5917892456054688,
        0.3578190803527832,
        0.0
      ],
      "openness": 2.303232431411743,
      "palm_size": 0.01612764410674572,
      "scale_hint": 0.24,
      "anchors": {
        "forehead": [
          0.5,
          0.23999999463558197,
          0.0
        ],
        "mouth": [
          0.5,
          0.3499999940395355,
          0.0
        ],
        "chin": [
          0.5,
          0.41999998688697815,
          0.0
        ],
        "left_shoulder": [
          0.3799999952316284,
          0.6200000047683716,
          0.0
        ],
        "right_shoulder": [
          0.6200000047683716,
          0.6200000047683716,
          0.0
        ],
        "shoulder_center": [
          0.5,
          0.6200000047683716,
          0.0
        ],
        "nose": [
          0.5,
          0.3100000023841858,
          0.0
        ],
        "scale_hint": 0.24
      }
    },
    {
      "handedness": "right",
      "hand_landmarks": [
        [
          0.5757777094841003,
          0.3799999952316284,
          0.0
        ],
        [
          0.5825777053833008,
          0.3782999813556671,
          0.0
        ],
        [
          0.5859777331352234,
          0.3748999834060669,
          0.0
        ],
        [
          0.5893777012825012,
          0.3714999854564667,
          0.0
        ],
        [
          0.5944777131080627,
          0.36980000138282776,
          0.0
        ],
        [
          0.5808777213096619,
          0.3630000054836273,
          0.0
        ],
        [
          0.5808777213096619,
          0.3425999879837036,
          0.0
        ],
        [
          0.5808777213096619,
          0.3188000023365021,
          0.0
        ],
        [
          0.5808777213096619,
          0.29159998893737793,
          0.0
        ],
        [
          0.5757777094841003,
          0.36640000343322754,
          0.0
        ],
        [
          0.5757777094841003,
          0.3596000075340271,
          0.0
        ],
        [
          0.5757777094841003,
          0.3544999957084656,
          0.0
        ],
        [
          0.5757777094841003,
          0.3527999818325043,
          0.0
        ],
        [
          0.5706776976585388,
          0.36640000343322754,
          0.0
        ],
        [
          0.5706776976585388,
          0.361299991607666,
          0.0
        ],
        [
          0.5706776976585388,
          0.3578999936580658,
          0.0
        ],
        [
          0.5706776976585388,
          0.3561999797821045,
          0.0
        ],
        [
          0.5655776858329773,
          0.36809998750686646,
          0.0
        ],
        [
          0.5655776858329773,
          0.3630000054836273,
          0.0
        ],
        [
          0.5655776858329773,
          0.3596000075340271,
          0.0
        ],
        [
          0.5655776858329773,
          0.3578999936580658,
          0.0
        ]
      ],
      "hand_center": [
        0.5761824250221252,
        0.3578190803527832,
        0.0
      ],
      "openness": 2.303232431411743,
      "palm_size": 0.01612764410674572,
      "scale_hint": 0.24,
      "anchors": {
        "forehead": [
          0.5,
          0.23999999463558197,
          0.0
        ],
        "mouth": [
          0.5,
          0.3499999940395355,
          0.0
        ],
        "chin": [
          0.5,
          0.41999998688697815,
          0.0
        ],
        "left_shoulder": [
          0.3799999952316284,
          0.6200000047683716,
          0.0
        ],
        "right_shoulder": [
          0.6200000047683716,
          0.6200000047683716,
          0.0
        ],
        "shoulder_center": [
          0.5,
          0.6200000047683716,
          0.0
        ],
        "nose": [
          0.5,
          0.3100000023841858,
          0.0
        ],
        "scale_hint": 0.24
      }
    },
    {
      "handedness": "right",
      "hand_landmarks": [
        [
          0.5554059743881226,
          0.3799999952316284,
          0.0
        ],
        [
          0.562205970287323,
          0.3782999813556671,
          0.0
        ],
        [
          0.5656059980392456,
          0.3748999834060669,
          0.0
        ],
        [
          0.5690059661865234,
          0.3714999854564667,
          0.0
        ],
        [
          0.574105978012085,
          0.36980000138282776,
          0.0
        ],
        [
          0.5605059862136841,
          0.3630000054836273,
          0.0
        ],
        [
          0.5605059862136841,
          0.3425999879837036,
          0.0
        ],
        [
          0.5605059862136841,
          0.3188000023365021,
          0.0
        ],
        [
          0.5605059862136841,
          0.29159998893737793,
          0.0
        ],
        [
          0.5554059743881226,
          0.36640000343322754,
          0.0
        ],
        [
          0.5554059743881226,
          0.3596000075340271,
          0.0
        ],
        [
          0.5554059743881226,
          0.3544999957084656,
          0.0
        ],
        [
          0.5554059743881226,
          0.3527999818325043,
          0.0
        ],
        [
          0.550305962562561,
          0.36640000343322754,
          0.0
        ],
        [
          0.550305962562561,
          0.361299991607666,
          0.0
        ],
        [
          0.550305962562561,
          0.3578999936580658,
          0.0
        ],
        [
          0.550305962562561,
          0.3561999797821045,
          0.0
        ],
        [
          0.5452059507369995,
          0.36809998750686646,
          0.0
        ],
        [
          0.5452059507369995,
          0.3630000054836273,
          0.0
        ],
        [
          0.5452059507369995,
          0.3596000075340271,
          0.0
        ],
        [
          0.5452059507369995,
          0.3578999936580658,
          0.0
        ]
      ],
      "hand_center": [
        0.555810809135437,
        0.3578190803527832,
        0.0
      ],
      "openness": 2.303232431411743,
      "palm_size": 0.01612764410674572,
      "scale_hint": 0.24,
      "anchors": {
        "forehead": [
          0.5,
          0.23999999463558197,
          0.0
        ],
        "mouth": [
          0.5,
          0.3499999940395355,
          0.0
        ],
        "chin": [
          0.5,
          0.41999998688697815,
          0.0
        ],
        "left_shoulder": [
          0.3799999952316284,
          0.6200000047683716,
          0.0
        ],
        "right_shoulder": [
          0.6200000047683716,
          0.6200000047683716,
          0.0
        ],
        "shoulder_center": [
          0.5,
          0.6200000047683716,
          0.0
        ],
        "nose": [
          0.5,
          0.3100000023841858,
          0.0
        ],
        "scale_hint": 0.24
      }
    },
    {
      "handedness": "right",
      "hand_landmarks": [
        [
          0.5340349078178406,
          0.3799999952316284,
          0.0
        ],
        [
          0.540834903717041,
          0.3782999813556671,
          0.0
        ],
        [
          0.5442349314689636,
          0.3748999834060669,
          0.0
        ],
        [
          0.5476348996162415,
          0.3714999854564667,
          0.0
        ],
        [
          0.552734911441803,
          0.36980000138282776,
          0.0
        ],
        [
          0.5391349196434021,
          0.3630000054836273,
          0.0
        ],
        [
          0.5391349196434021,
          0.3425999879837036,
          0.0
        ],
        [
          0.5391349196434021,
          0.3188000023365021,
          0.0
        ],
        [
          0.5391349196434021,
          0.29159998893737793,
          0.0
        ],
        [
          0.5340349078178406,
          0.36640000343322754,
          0.0
        ],
        [
          0.5340349078178406,
          0.3596000075340271,
          0.0
        ],
        [
          0.5340349078178406,
          0.3544999957084656,
          0.0
        ],
        [
          0.5340349078178406,
          0.3527999818325043,
          0.0
        ],
        [
          0.528934895992279,
          0.36640000343322754,
          0.0
        ],
        [
          0.528934895992279,
          0.361299991607666,
          0.0
        ],
        [
          0.528934895992279,
          0.3578999936580658,
          0.0
        ],
        [
          0.528934895992279,
          0.3561999797821045,
          0.0
        ],
        [
          0.5238348841667175,
          0.36809998750686646,
          0.0
        ],
        [
          0.5238348841667175,
          0.3630000054836273,
          0.0
        ],
        [
          0.5238348841667175,
          0.3596000075340271,
          0.0
        ],
        [
          0.5238348841667175,
          0.3578999936580658,
          0.0
        ]
      ],
      "hand_center": [
        0.5344396233558655,
        0.3578190803527832,
        0.0
      ],
      "openness": 2.303232431411743,
      "palm_size": 0.01612764410674572,
      "scale_hint": 0.24,
      "anchors": {
        "forehead": [
          0.5,
          0.23999999463558197,
          0.0
        ],
        "mouth": [
          0.5,
          0.3499999940395355,
          0.0
        ],
        "chin": [
          0.5,
          0.41999998688697815,
          0.0
        ],
        "left_shoulder": [
          0.3799999952316284,
          0.6200000047683716,
          0.0
        ],
        "right_shoulder": [
          0.6200000047683716,
          0.6200000047683716,
          0.0
        ],
        "shoulder_center": [
          0.5,
          0.6200000047683716,
          0.0
        ],
        "nose": [
          0.5,
          0.3100000023841858,
          0.0
        ],
        "scale_hint": 0.24
      }
    },
    {
      "handedness": "right",
      "hand_landmarks": [
        [
          0.5156150460243225,
          0.3799999952316284,
          0.0
        ],
        [
          0.522415041923523,
          0.3782999813556671,
          0.0
        ],
        [
          0.5258150696754456,
          0.3748999834060669,
          0.0
        ],
        [
          0.5292150378227234,
          0.3714999854564667,
          0.0
        ],
        [
          0.5343150496482849,
          0.36980000138282776,
          0.0
        ],
        [
          0.520715057849884,
          0.3630000054836273,
          0.0
        ],
        [
          0.520715057849884,
          0.3425999879837036,
          0.0
        ],
        [
          0.520715057849884,
          0.3188000023365021,
          0.0
        ],
        [
          0.520715057849884,
          0.29159998893737793,
          0.0
        ],
        [
          0.5156150460243225,
          0.36640000343322754,
          0.0
        ],
        [
          0.5156150460243225,
          0.3596000075340271,
          0.0
        ],
        [
          0.5156150460243225,
          0.3544999957084656,
          0.0
        ],
        [
          0.5156150460243225,
          0.3527999818325043,
          0.0
        ],
        [
          0.510515034198761,
          0.36640000343322754,
          0.0
        ],
        [
          0.510515034198761,
          0.361299991607666,
          0.0
        ],
        [
          0.510515034198761,
          0.3578999936580658,
          0.0
        ],
        [
          0.510515034198761,
          0.3561999797821045,
          0.0
        ],
        [
          0.5054150223731995,
          0.36809998750686646,
          0.0
        ],
        [
          0.5054150223731995,
          0.3630000054836273,
          0.0
        ],
        [
          0.5054150223731995,
          0.3596000075340271,
          0.0
        ],
        [
          0.5054150223731995,
          0.3578999936580658,
          0.0
        ]
      ],
      "hand_center": [
        0.5160198211669922,
        0.3578190803527832,
        0.0
      ],
      "openness": 2.303232431411743,
      "palm_size": 0.01612764410674572,
      "scale_hint": 0.24,
      "anchors": {
        "forehead": [
          0.5,
          0.23999999463558197,
          0.0
        ],
        "mouth": [
          0.5,
          0.3499999940395355,
          0.0
        ],
        "chin": [
          0.5,
          0.41999998688697815,
          0.0
        ],
        "left_shoulder": [
          0.3799999952316284,
          0.6200000047683716,
          0.0
        ],
        "right_shoulder": [
          0.6200000047683716,
          0.6200000047683716,
          0.0
        ],
        "shoulder_center": [
          0.5,
          0.6200000047683716,
          0.0
        ],
        "nose": [
          0.5,
          0.3100000023841858,
          0.0
        ],
        "scale_hint": 0.24
      }
    },
    {
      "handedness": "right",
      "hand_landmarks": [
        [
          0.503551185131073,
          0.3799999952316284,
          0.0
        ],
        [
          0.5103511810302734,
          0.3782999813556671,
          0.0
        ],
        [
          0.513751208782196,
          0.3748999834060669,
          0.0
        ],
        [
          0.5171511769294739,
          0.3714999854564667,
          0.0
        ],
        [
          0.5222511887550354,
          0.36980000138282776,
          0.0
        ],
        [
          0.5086511969566345,
          0.3630000054836273,
          0.0
        ],
        [
          0.5086511969566345,
          0.3425999879837036,
          0.0
        ],
        [
          0.5086511969566345,
          0.3188000023365021,
          0.0
        ],
        [
          0.5086511969566345,
          0.29159998893737793,
          0.0
        ],
        [
          0.503551185131073,
          0.36640000343322754,
          0.0
        ],
        [
          0.503551185131073,
          0.3596000075340271,
          0.0
        ],
        [
          0.503551185131073,
          0.3544999957084656,
          0.0
        ],
        [
          0.503551185131073,
          0.3527999818325043,
          0.0
        ],
        [
          0.4984511733055115,
          0.36640000343322754,
          0.0
        ],
        [
          0.4984511733055115,
          0.361299991607666,
          0.0
        ],
        [
          0.4984511733055115,
          0.3578999936580658,
          0.0
        ],
        [
          0.4984511733055115,
          0.3561999797821045,
          0.0
        ],
        [
          0.49335119128227234,
          0.36809998750686646,
          0.0
        ],
        [
          0.49335119128227234,
          0.3630000054836273,
          0.0
        ],
        [
          0.49335119128227234,
          0.3596000075340271,
          0.0
        ],
        [
          0.49335119128227234,
          0.3578999936580658,
          0.0
        ]
      ],
      "hand_center": [
        0.5039559006690979,
        0.3578190803527832,
        0.0
      ],
      "openness": 2.303236246109009,
      "palm_size": 0.01612761616706848,
      "scale_hint": 0.24,
      "anchors": {
        "forehead": [
          0.5,
          0.23999999463558197,
          0.0
        ],
        "mouth": [
          0.5,
          0.3499999940395355,
          0.0
        ],
        "chin": [
          0.5,
          0.41999998688697815,
          0.0
        ],
        "left_shoulder": [
          0.3799999952316284,
          0.6200000047683716,
          0.0
        ],
        "right_shoulder": [
          0.6200000047683716,
          0.6200000047683716,
          0.0
        ],
        "shoulder_center": [
          0.5,
          0.6200000047683716,
          0.0
        ],
        "nose": [
          0.5,
          0.3100000023841858,
          0.0
        ],
        "scale_hint": 0.24
      }
    },
    {
      "handedness": "right",
      "hand_landmarks": [
        [
          0.5000733137130737,
          0.3799999952316284,
          0.0
        ],
        [
          0.5068733096122742,
          0.3782999813556671,
          0.0
        ],
        [
          0.5102733373641968,
          0.3748999834060669,
          0.0
        ],
        [
          0.5136733055114746,
          0.3714999854564667,
          0.0
        ],
        [
          0.5187733173370361,
          0.36980000138282776,
          0.0
        ],
        [
          0.5051733255386353,
          0.3630000054836273,
          0.0
        ],
        [
          0.5051733255386353,
          0.3425999879837036,
          0.0
        ],
        [
          0.5051733255386353,
          0.3188000023365021,
          0.0
        ],
        [
          0.5051733255386353,
          0.29159998893737793,
          0.0
        ],
        [
          0.5000733137130737,
          0.36640000343322754,
          0.0
        ],
        [
          0.5000733137130737,
          0.3596000075340271,
          0.0
        ],
        [
          0.5000733137130737,
          0.3544999957084656,
          0.0
        ],
        [
          0.5000733137130737,
          0.3527999818325043,
          0.0
        ],
        [
          0.4949733018875122,
          0.36640000343322754,
          0.0
        ],
        [
          0.4949733018875122,
          0.361299991607666,
          0.0
        ],
        [
          0.4949733018875122,
          0.3578999936580658,
          0.0
        ],
        [
          0.4949733018875122,
          0.3561999797821045,
          0.0
        ],
        [
          0.48987331986427307,
          0.36809998750686646,
          0.0
        ],
        [
          0.48987331986427307,
          0.3630000054836273,
          0.0
        ],
        [
          0.48987331986427307,
          0.3596000075340271,
          0.0
        ],
        [
          0.48987331986427307,
          0.3578999936580658,
          0.0
        ]
      ],
      "hand_center": [
        0.5004780292510986,
        0.3578190803527832,
        0.0
      ],
      "openness": 2.303236246109009,
      "palm_size": 0.01612761616706848,
      "scale_hint": 0.24,
      "anchors": {
        "forehead": [
          0.5,
          0.23999999463558197,
          0.0
        ],
        "mouth": [
          0.5,
          0.3499999940395355,
          0.0
        ],
        "chin": [
          0.5,
          0.41999998688697815,
          0.0
        ],
        "left_shoulder": [
          0.3799999952316284,
          0.6200000047683716,
          0.0
        ],
        "right_shoulder": [
          0.6200000047683716,
          0.6200000047683716,
          0.0
        ],
        "shoulder_center": [
          0.5,
          0.6200000047683716,
          0.0
        ],
        "nose": [
          0.5,
          0.3100000023841858,
          0.0
        ],
        "scale_hint": 0.24
      }
    },
    {
      "handedness": "right",
      "hand_landmarks": [
        [
          0.5058243870735168,
          0.3799999952316284,
          0.0
        ],
        [
          0.5126243829727173,
          0.3782999813556671,
          0.0
        ],
        [
          0.5160244107246399,
          0.3748999834060669,
          0.0
        ],
        [
          0.5194243788719177,
          0.3714999854564667,
          0.0
        ],
        [
          0.5245243906974792,
          0.36980000138282776,
          0.0
        ],
        [
          0.5109243988990784,
          0.3630000054836273,
          0.0
        ],
        [
          0.5109243988990784,
          0.3425999879837036,
          0.0
        ],
        [
          0.5109243988990784,
          0.3188000023365021,
          0.0
        ],
        [
          0.5109243988990784,
          0.29159998893737793,
          0.0
        ],
        [
          0.5058243870735168,
          0.36640000343322754,
          0.0
        ],
        [
          0.5058243870735168,
          0.3596000075340271,
          0.0
        ],
        [
          0.5058243870735168,
          0.3544999957084656,
          0.0
        ],
        [
          0.5058243870735168,
          0.3527999818325043,
          0.0
        ],
        [
          0.5007243752479553,
          0.36640000343322754,
          0.0
        ],
        [
          0.5007243752479553,
          0.361299991607666,
          0.0
        ],
        [
          0.5007243752479553,
          0.3578999936580658,
          0.0
        ],
        [
          0.5007243752479553,
          0.3561999797821045,
          0.0
        ],
        [
          0.4956243932247162,
          0.36809998750686646,
          0.0
        ],
        [
          0.4956243932247162,
          0.3630000054836273,
          0.0
        ],
        [
          0.4956243932247162,
          0.3596000075340271,
          0.0
        ],
        [
          0.4956243932247162,
          0.3578999936580658,
          0.0
        ]
      ],
      "hand_center": [
        0.5062292218208313,
        0.3578190803527832,
        0.0
      ],
      "openness": 2.303236246109009,
      "palm_size": 0.01612761616706848,
      "scale_hint": 0.24,
      "anchors": {
        "forehead": [
          0.5,
          0.23999999463558197,
          0.0
        ],
        "mouth": [
          0.5,
          0.3499999940395355,
          0.0
        ],
        "chin": [
          0.5,
          0.41999998688697815,
          0.0
        ],
        "left_shoulder": [
          0.3799999952316284,
          0.6200000047683716,
          0.0
        ],
        "right_shoulder": [
          0.6200000047683716,
          0.6200000047683716,
          0.0
        ],
        "shoulder_center": [
          0.5,
          0.6200000047683716,
          0.0
        ],
        "nose": [
          0.5,
          0.3100000023841858,
          0.0
        ],
        "scale_hint": 0.24
      }
    },
    {
      "handedness": "right",
      "hand_landmarks": [
        [
          0.5197412967681885,
          0.3799999952316284,
          0.0
        ],
        [
          0.5265412926673889,
          0.3782999813556671,
          0.0
        ],
        [
          0.5299413204193115,
          0.3748999834060669,
          0.0
        ],
        [
          0.5333412885665894,
          0.3714999854564667,
          0.0
        ],
        [
          0.5384413003921509,
          0.36980000138282776,
          0.0
        ],
        [
          0.52484130859375,
          0.3630000054836273,
          0.0
        ],
        [
          0.52484130859375,
          0.3425999879837036,
          0.0
        ],
        [
          0.52484130859375,
          0.3188000023365021,
          0.0
        ],
        [
          0.52484130859375,
          0.29159998893737793,
          0.0
        ],
        [
          0.5197412967681885,
          0.36640000343322754,
          0.0
        ],
        [
          0.5197412967681885,
          0.3596000075340271,
          0.0
        ],
        [
          0.5197412967681885,
          0.3544999957084656,
          0.0
        ],
        [
          0.5197412967681885,
          0.3527999818325043,
          0.0
        ],
        [
          0.514641284942627,
          0.36640000343322754,
          0.0
        ],
        [
          0.514641284942627,
          0.361299991607666,
          0.0
        ],
        [
          0.514641284942627,
          0.3578999936580658,
          0.0
        ],
        [
          0.514641284942627,
          0.3561999797821045,
          0.0
        ],
        [
          0.5095412731170654,
          0.36809998750686646,
          0.0
        ],
        [
          0.5095412731170654,
          0.3630000054836273,
          0.0
        ],
        [
          0.5095412731170654,
          0.3596000075340271,
          0.0
        ],
        [
          0.5095412731170654,
          0.3578999936580658,
          0.0
        ]
      ],
      "hand_center": [
        0.5201460719108582,
        0.3578190803527832,
        0.0
      ],
      "openness": 2.303232431411743,
      "palm_size": 0.01612764410674572,
      "scale_hint": 0.24,
      "anchors": {
        "forehead": [
          0.5,
          0.23999999463558197,
          0.0
        ],
        "mouth": [
          0.5,
          0.3499999940395355,
          0.0
        ],
        "chin": [
          0.5,
          0.41999998688697815,
          0.0
        ],
        "left_shoulder": [
          0.3799999952316284,
          0.6200000047683716,
          0.0
        ],
        "right_shoulder": [
          0.6200000047683716,
          0.6200000047683716,
          0.0
        ],
        "shoulder_center": [
          0.5,
          0.6200000047683716,
          0.0
        ],
        "nose": [
          0.5,
          0.3100000023841858,
          0.0
        ],
        "scale_hint": 0.24
      }
    },
    {
      "handedness": "right",
      "hand_landmarks": [
        [
          0.5392515063285828,
          0.3799999952316284,
          0.0
        ],
        [
          0.5460515022277832,
          0.3782999813556671,
          0.0
        ],
        [
          0.5494515299797058,
          0.3748999834060669,
          0.0
        ],
        [
          0.5528514981269836,
          0.3714999854564667,
          0.0
        ],
        [
          0.5579515099525452,
          0.36980000138282776,
          0.0
        ],
        [
          0.5443515181541443,
          0.3630000054836273,
          0.0
        ],
        [
          0.5443515181541443,
          0.3425999879837036,
          0.0
        ],
        [
          0.5443515181541443,
          0.3188000023365021,
          0.0
        ],
        [
          0.5443515181541443,
          0.29159998893737793,
          0.0
        ],
        [
          0.5392515063285828,
          0.36640000343322754,
          0.0
        ],
        [
          0.5392515063285828,
          0.3596000075340271,
          0.0
        ],
        [
          0.5392515063285828,
          0.3544999957084656,
          0.0
        ],
        [
          0.5392515063285828,
          0.3527999818325043,
          0.0
        ],
        [
          0.5341514945030212,
          0.36640000343322754,
          0.0
        ],
        [
          0.5341514945030212,
          0.361299991607666,
          0.0
        ],
        [
          0.5341514945030212,
          0.3578999936580658,
          0.0
        ],
        [
          0.5341514945030212,
          0.3561999797821045,
          0.0
        ],
        [
          0.5290514826774597,
          0.36809998750686646,
          0.0
        ],
        [
          0.5290514826774597,
          0.3630000054836273,
          0.0
        ],
        [
          0.5290514826774597,
          0.3596000075340271,
          0.0
        ],
        [
          0.5290514826774597,
          0.3578999936580658,
          0.0
        ]
      ],
      "hand_center": [
        0.5396562218666077,
        0.3578190803527832,
        0.0
      ],
      "openness": 2.303232431411743,
      "palm_size": 0.01612764410674572,
      "scale_hint": 0.24,
      "anchors": {
        "forehead": [
          0.5,
          0.23999999463558197,
          0.0
        ],
        "mouth": [
          0.5,
          0.3499999940395355,
          0.0
        ],
        "chin": [
          0.5,
          0.41999998688697815,
          0.0
        ],
        "left_shoulder": [
          0.3799999952316284,
          0.6200000047683716,
          0.0
        ],
        "right_shoulder": [
          0.6200000047683716,
          0.6200000047683716,
          0.0
        ],
        "shoulder_center": [
          0.5,
          0.6200000047683716,
          0.0
        ],
        "nose": [
          0.5,
          0.3100000023841858,
          0.0
        ],
        "scale_hint": 0.24
      }
    },
    {
      "handedness": "right",
      "hand_landmarks": [
        [
          0.5607485175132751,
          0.3799999952316284,
          0.0
        ],
        [
          0.5675485134124756,
          0.3782999813556671,
          0.0
        ],
        [
          0.5709485411643982,
          0.3748999834060669,
          0.0
        ],
        [
          0.574348509311676,
          0.3714999854564667,
          0.0
        ],
        [
          0.5794485211372375,
          0.36980000138282776,
          0.0
        ],
        [
          0.5658485293388367,
          0.3630000054836273,
          0.0
        ],
        [
          0.5658485293388367,
          0.3425999879837036,
          0.0
        ],
        [
          0.5658485293388367,
          0.3188000023365021,
          0.0
        ],
        [
          0.5658485293388367,
          0.29159998893737793,
          0.0
        ],
        [
          0.5607485175132751,
          0.36640000343322754,
          0.0
        ],
        [
          0.5607485175132751,
          0.3596000075340271,
          0.0
        ],
        [
          0.5607485175132751,
          0.3544999957084656,
          0.0
        ],
        [
          0.5607485175132751,
          0.3527999818325043,
          0.0
        ],
        [
          0.5556485056877136,
          0.36640000343322754,
          0.0
        ],
        [
          0.5556485056877136,
          0.361299991607666,
          0.0
        ],
        [
          0.5556485056877136,
          0.3578999936580658,
          0.0
        ],
        [
          0.5556485056877136,
          0.3561999797821045,
          0.0
        ],
        [
          0.5505484938621521,
          0.36809998750686646,
          0.0
        ],
        [
          0.5505484938621521,
          0.3630000054836273,
          0.0
        ],
        [
          0.5505484938621521,
          0.3596000075340271,
          0.0
        ],
        [
          0.5505484938621521,
          0.3578999936580658,
          0.0
        ]
      ],
      "hand_center": [
        0.5611532926559448,
        0.3578190803527832,
        0.0
      ],
      "openness": 2.303232431411743,
      "palm_size": 0.01612764410674572,
      "scale_hint": 0.24,
      "anchors": {
        "forehead": [
          0.5,
          0.23999999463558197,
          0.0
        ],
        "mouth": [
          0.5,
          0.3499999940395355,
          0.0
        ],
        "chin": [
          0.5,
          0.41999998688697815,
          0.0
        ],
        "left_shoulder": [
          0.3799999952316284,
          0.6200000047683716,
          0.0
        ],
        "right_shoulder": [
          0.6200000047683716,
          0.6200000047683716,
          0.0
        ],
        "shoulder_center": [
          0.5,
          0.6200000047683716,
          0.0
        ],
        "nose": [
          0.5,
          0.3100000023841858,
          0.0
        ],
        "scale_hint": 0.24
      }
    },
    {
      "handedness": "right",
      "hand_landmarks": [
        [
          0.5802587270736694,
          0.3799999952316284,
          0.0
        ],
        [
          0.5870587229728699,
          0.3782999813556671,
          0.0
        ],
        [
          0.5904587507247925,
          0.3748999834060669,
          0.0
        ],
        [
          0.5938587188720703,
          0.3714999854564667,
          0.0
        ],
        [
          0.5989587306976318,
          0.36980000138282776,
          0.0
        ],
        [
          0.585358738899231,
          0.3630000054836273,
          0.0
        ],
        [
          0.585358738899231,
          0.3425999879837036,
          0.0
        ],
        [
          0.585358738899231,
          0.3188000023365021,
          0.0
        ],
        [
          0.585358738899231,
          0.29159998893737793,
          0.0
        ],
        [
          0.5802587270736694,
          0.36640000343322754,
          0.0
        ],
        [
          0.5802587270736694,
          0.3596000075340271,
          0.0
        ],
        [
          0.5802587270736694,
          0.3544999957084656,
          0.0
        ],
        [
          0.5802587270736694,
          0.3527999818325043,
          0.0
        ],
        [
          0.5751587152481079,
          0.36640000343322754,
          0.0
        ],
        [
          0.5751587152481079,
          0.361299991607666,
          0.0
        ],
        [
          0.5751587152481079,
          0.3578999936580658,
          0.0
        ],
        [
          0.5751587152481079,
          0.3561999797821045,
          0.0
        ],
        [
          0.5700587034225464,
          0.36809998750686646,
          0.0
        ],
        [
          0.5700587034225464,
          0.3630000054836273,
          0.0
        ],
        [
          0.5700587034225464,
          0.3596000075340271,
          0.0
        ],
        [
          0.5700587034225464,
          0.3578999936580658,
          0.0
        ]
      ],
      "hand_center": [
        0.5806635618209839,
        0.3578190803527832,
        0.0
      ],
      "openness": 2.303232431411743,
      "palm_size": 0.01612764410674572,
      "scale_hint": 0.24,
      "anchors": {
        "forehead": [
          0.5,
          0.23999999463558197,
          0.0
        ],
        "mouth": [
          0.5,
          0.3499999940395355,
          0.0
        ],
        "chin": [
          0.5,
          0.41999998688697815,
          0.0
        ],
        "left_shoulder": [
          0.3799999952316284,
          0.6200000047683716,
          0.0
        ],
        "right_shoulder": [
          0.6200000047683716,
          0.6200000047683716,
          0.0
        ],
        "shoulder_center": [
          0.5,
          0.6200000047683716,
          0.0
        ],
        "nose": [
          0.5,
          0.3100000023841858,
          0.0
        ],
        "scale_hint": 0.24
      }
    },
    {
      "handedness": "right",
      "hand_landmarks": [
        [
          0.5941756367683411,
          0.3799999952316284,
          0.0
        ],
        [
          0.6009756326675415,
          0.3782999813556671,
          0.0
        ],
        [
          0.6043756604194641,
          0.3748999834060669,
          0.0
        ],
        [
          0.6077756285667419,
          0.3714999854564667,
          0.0
        ],
        [
          0.6128756403923035,
          0.36980000138282776,
          0.0
        ],
        [
          0.5992756485939026,
          0.3630000054836273,
          0.0
        ],
        [
          0.5992756485939026,
          0.3425999879837036,
          0.0
        ],
        [
          0.5992756485939026,
          0.3188000023365021,
          0.0
        ],
        [
          0.5992756485939026,
          0.29159998893737793,
          0.0
        ],
        [
          0.5941756367683411,
          0.36640000343322754,
          0.0
        ],
        [
          0.5941756367683411,
          0.3596000075340271,
          0.0
        ],
        [
          0.5941756367683411,
          0.3544999957084656,
          0.0
        ],
        [
          0.5941756367683411,
          0.3527999818325043,
          0.0
        ],
        [
          0.5890756249427795,
          0.36640000343322754,
          0.0
        ],
        [
          0.5890756249427795,
          0.361299991607666,
          0.0
        ],
        [
          0.5890756249427795,
          0.3578999936580658,
          0.0
        ],
        [
          0.5890756249427795,
          0.3561999797821045,
          0.0
        ],
        [
          0.583975613117218,
          0.36809998750686646,
          0.0
        ],
        [
          0.583975613117218,
          0.3630000054836273,
          0.0
        ],
        [
          0.583975613117218,
          0.3596000075340271,
          0.0
        ],
        [
          0.583975613117218,
          0.3578999936580658,
          0.0
        ]
      ],
      "hand_center": [
        0.5945805311203003,
        0.3578190803527832,
        0.0
      ],
      "openness": 2.303232431411743,
      "palm_size": 0.01612764410674572,
      "scale_hint": 0.24,
      "anchors": {
        "forehead": [
          0.5,
          0.23999999463558197,
          0.0
        ],
        "mouth": [
          0.5,
          0.3499999940395355,
          0.0
        ],
        "chin": [
          0.5,
          0.41999998688697815,
          0.0
        ],
        "left_shoulder": [
          0.3799999952316284,
          0.6200000047683716,
          0.0
        ],
        "right_shoulder": [
          0.6200000047683716,
          0.6200000047683716,
          0.0
        ],
        "shoulder_center": [
          0.5,
          0.6200000047683716,
          0.0
        ],
        "nose": [
          0.5,
          0.3100000023841858,
          0.0
        ],
        "scale_hint": 0.24
      }
    },
    {
      "handedness": "right",
      "hand_landmarks": [
        [
          0.5999267101287842,
          0.3799999952316284,
          0.0
        ],
        [
          0.6067267060279846,
          0.3782999813556671,
          0.0
        ],
        [
          0.6101267337799072,
          0.3748999834060669,
          0.0
        ],
        [
          0.6135267019271851,
          0.3714999854564667,
          0.0
        ],
        [
          0.6186267137527466,
          0.36980000138282776,
          0.0
        ],
        [
          0.6050267219543457,
          0.3630000054836273,
          0.0
        ],
        [
          0.6050267219543457,
          0.3425999879837036,
          0.0
        ],
        [
          0.6050267219543457,
          0.3188000023365021,
          0.0
        ],
        [
          0.6050267219543457,
          0.29159998893737793,
          0.0
        ],
        [
          0.5999267101287842,
          0.36640000343322754,
          0.0
        ],
        [
          0.5999267101287842,
          0.3596000075340271,
          0.0
        ],
        [
          0.5999267101287842,
          0.3544999957084656,
          0.0
        ],
        [
          0.5999267101287842,
          0.3527999818325043,
          0.0
        ],
        [
          0.5948266983032227,
          0.36640000343322754,
          0.0
        ],
        [
          0.5948266983032227,
          0.361299991607666,
          0.0
        ],
        [
          0.5948266983032227,
          0.3578999936580658,
          0.0
        ],
        [
          0.5948266983032227,
          0.3561999797821045,
          0.0
        ],
        [
          0.5897266864776611,
          0.36809998750686646,
          0.0
        ],
        [
          0.5897266864776611,
          0.3630000054836273,
          0.0
        ],
        [
          0.5897266864776611,
          0.3596000075340271,
          0.0
        ],
        [
          0.5897266864776611,
          0.3578999936580658,
          0.0
        ]
      ],
      "hand_center": [
        0.6003314256668091,
        0.3578190803527832,
        0.0
      ],
      "openness": 2.303232431411743,
      "palm_size": 0.01612764410674572,
      "scale_hint": 0.24,
      "anchors": {
        "forehead": [
          0.5,
          0.23999999463558197,
          0.0
        ],
        "mouth": [
          0.5,
          0.3499999940395355,
          0.0
        ],
        "chin": [
          0.5,
          0.41999998688697815,
          0.0
        ],
        "left_shoulder": [
          0.3799999952316284,
          0.6200000047683716,
          0.0
        ],
        "right_shoulder": [
          0.6200000047683716,
          0.6200000047683716,
          0.0
        ],
        "shoulder_center": [
          0.5,
          0.6200000047683716,
          0.0
        ],
        "nose": [
          0.5,
          0.3100000023841858,
          0.0
        ],
        "scale_hint": 0.24
      }
    },
    {
      "handedness": "right",
      "hand_landmarks": [
        [
          0.5964488387107849,
          0.3799999952316284,
          0.0
        ],
        [
          0.6032488346099854,
          0.3782999813556671,
          0.0
        ],
        [
          0.606648862361908,
          0.3748999834060669,
          0.0
        ],
        [
          0.6100488305091858,
          0.3714999854564667,
          0.0
        ],
        [
          0.6151488423347473,
          0.36980000138282776,
          0.0
        ],
        [
          0.6015488505363464,
          0.3630000054836273,
          0.0
        ],
        [
          0.6015488505363464,
          0.3425999879837036,
          0.0
        ],
        [
          0.6015488505363464,
          0.3188000023365021,
          0.0
        ],
        [
          0.6015488505363464,
          0.29159998893737793,
          0.0
        ],
        [
          0.5964488387107849,
          0.36640000343322754,
          0.0
        ],
        [
          0.5964488387107849,
          0.3596000075340271,
          0.0
        ],
        [
          0.5964488387107849,
          0.3544999957084656,
          0.0
        ],
        [
          0.5964488387107849,
          0.3527999818325043,
          0.0
        ],
        [
          0.5913488268852234,
          0.36640000343322754,
          0.0
        ],
        [
          0.5913488268852234,
          0.361299991607666,
          0.0
        ],
        [
          0.5913488268852234,
          0.3578999936580658,
          0.0
        ],
        [
          0.5913488268852234,
          0.3561999797821045,
          0.0
        ],
        [
          0.5862488150596619,
          0.36809998750686646,
          0.0
        ],
        [
          0.5862488150596619,
          0.3630000054836273,
          0.0
        ],
        [
          0.5862488150596619,
          0.3596000075340271,
          0.0
        ],
        [
          0.5862488150596619,
          0.3578999936580658,
          0.0
        ]
      ],
      "hand_center": [
        0.596853494644165,
        0.3578190803527832,
        0.0
      ],
      "openness": 2.303232431411743,
      "palm_size": 0.01612764410674572,
      "scale_hint": 0.24,
      "anchors": {
        "forehead": [
          0.5,
          0.23999999463558197,
          0.0
        ],
        "mouth": [
          0.5,
          0.3499999940395355,
          0.0
        ],
        "chin": [
          0.5,
          0.41999998688697815,
          0.0
        ],
        "left_shoulder": [
          0.3799999952316284,
          0.6200000047683716,
          0.0
        ],
        "right_shoulder": [
          0.6200000047683716,
          0.6200000047683716,
          0.0
        ],
        "shoulder_center": [
          0.5,
          0.6200000047683716,
          0.0
        ],
        "nose": [
          0.5,
          0.3100000023841858,
          0.0
        ],
        "scale_hint": 0.24
      }
    },
    {
      "handedness": "right",
      "hand_landmarks": [
        [
          0.5843849778175354,
          0.3799999952316284,
          0.0
        ],
        [
          0.5911849737167358,
          0.3782999813556671,
          0.0
        ],
        [
          0.5945850014686584,
          0.3748999834060669,
          0.0
        ],
        [
          0.5979849696159363,
          0.3714999854564667,
          0.0
        ],
        [
          0.6030849814414978,
          0.36980000138282776,
          0.0
        ],
        [
          0.5894849896430969,
          0.3630000054836273,
          0.0
        ],
        [
          0.5894849896430969,
          0.3425999879837036,
          0.0
        ],
        [
          0.5894849896430969,
          0.3188000023365021,
          0.0
        ],
        [
          0.5894849896430969,
          0.29159998893737793,
          0.0
        ],
        [
          0.5843849778175354,
          0.36640000343322754,
          0.0
        ],
        [
          0.5843849778175354,
          0.3596000075340271,
          0.0
        ],
        [
          0.5843849778175354,
          0.3544999957084656,
          0.0
        ],
        [
          0.5843849778175354,
          0.3527999818325043,
          0.0
        ],
        [
          0.5792849659919739,
          0.36640000343322754,
          0.0
        ],
        [
          0.5792849659919739,
          0.361299991607666,
          0.0
        ],
        [
          0.5792849659919739,
          0.3578999936580658,
          0.0
        ],
        [
          0.5792849659919739,
          0.3561999797821045,
          0.0
        ],
        [
          0.5741849541664124,
          0.36809998750686646,
          0.0
        ],
        [
          0.5741849541664124,
          0.3630000054836273,
          0.0
        ],
        [
          0.5741849541664124,
          0.3596000075340271,
          0.0
        ],
        [
          0.5741849541664124,
          0.3578999936580658,
          0.0
        ]
      ],
      "hand_center": [
        0.5847897529602051,
        0.3578190803527832,
        0.0
      ],
      "openness": 2.303232431411743,
      "palm_size": 0.01612764410674572,
      "scale_hint": 0.24,
      "anchors": {
        "forehead": [
          0.5,
          0.23999999463558197,
          0.0
        ],
        "mouth": [
          0.5,
          0.3499999940395355,
          0.0
        ],
        "chin": [
          0.5,
          0.41999998688697815,
          0.0
        ],
        "left_shoulder": [
          0.3799999952316284,
          0.6200000047683716,
          0.0
        ],
        "right_shoulder": [
          0.6200000047683716,
          0.6200000047683716,
          0.0
        ],
        "shoulder_center": [
          0.5,
          0.6200000047683716,
          0.0
        ],
        "nose": [
          0.5,
          0.3100000023841858,
          0.0
        ],
        "scale_hint": 0.24
      }
    },
    {
      "handedness": "right",
      "hand_landmarks": [
        [
          0.5659650564193726,
          0.3799999952316284,
          0.0
        ],
        [
          0.572765052318573,
          0.3782999813556671,
          0.0
        ],
        [
          0.5761650800704956,
          0.3748999834060669,
          0.0
        ],
        [
          0.5795650482177734,
          0.3714999854564667,
          0.0
        ],
        [
          0.584665060043335,
          0.36980000138282776,
          0.0
        ],
        [
          0.5710650682449341,
          0.3630000054836273,
          0.0
        ],
        [
          0.5710650682449341,
          0.3425999879837036,
          0.0
        ],
        [
          0.5710650682449341,
          0.3188000023365021,
          0.0
        ],
        [
          0.5710650682449341,
          0.29159998893737793,
          0.0
        ],
        [
          0.5659650564193726,
          0.36640000343322754,
          0.0
        ],
        [
          0.5659650564193726,
          0.3596000075340271,
          0.0
        ],
        [
          0.5659650564193726,
          0.3544999957084656,
          0.0
        ],
        [
          0.5659650564193726,
          0.3527999818325043,
          0.0
        ],
        [
          0.560865044593811,
          0.36640000343322754,
          0.0
        ],
        [
          0.560865044593811,
          0.361299991607666,
          0.0
        ],
        [
          0.560865044593811,
          0.3578999936580658,
          0.0
        ],
        [
          0.560865044593811,
          0.3561999797821045,
          0.0
        ],
        [
          0.5557650327682495,
          0.36809998750686646,
          0.0
        ],
        [
          0.5557650327682495,
          0.3630000054836273,
          0.0
        ],
        [
          0.5557650327682495,
          0.3596000075340271,
          0.0
        ],
        [
          0.5557650327682495,
          0.3578999936580658,
          0.0
        ]
      ],
      "hand_center": [
        0.566369891166687,
        0.3578190803527832,
        0.0
      ],
      "openness": 2.303232431411743,
      "palm_size": 0.01612764410674572,
      "scale_hint": 0.24,
      "anchors": {
        "forehead": [
          0.5,
          0.23999999463558197,
          0.0
        ],
        "mouth": [
          0.5,
          0.3499999940395355,
          0.0
        ],
        "chin": [
          0.5,
          0.41999998688697815,
          0.0
        ],
        "left_shoulder": [
          0.3799999952316284,
          0.6200000047683716,
          0.0
        ],
        "right_shoulder": [
          0.6200000047683716,
          0.6200000047683716,
          0.0
        ],
        "shoulder_center": [
          0.5,
          0.6200000047683716,
          0.0
        ],
        "nose": [
          0.5,
          0.3100000023841858,
          0.0
        ],
        "scale_hint": 0.24
      }
    },
    {
      "handedness": "right",
      "hand_landmarks": [
        [
          0.5445940494537354,
          0.3799999952316284,
          0.0
        ],
        [
          0.5513940453529358,
          0.3782999813556671,
          0.0
        ],
        [
          0.5547940731048584,
          0.3748999834060669,
          0.0
        ],
        [
          0.5581940412521362,
          0.3714999854564667,
          0.0
        ],
        [
          0.5632940530776978,
          0.36980000138282776,
          0.0
        ],
        [
          0.5496940612792969,
          0.3630000054836273,
          0.0
        ],
        [
          0.5496940612792969,
          0.3425999879837036,
          0.0
        ],
        [
          0.5496940612792969,
          0.3188000023365021,
          0.0
        ],
        [
          0.5496940612792969,
          0.29159998893737793,
          0.0
        ],
        [
          0.5445940494537354,
          0.36640000343322754,
          0.0
        ],
        [
          0.5445940494537354,
          0.3596000075340271,
          0.0
        ],
        [
          0.5445940494537354,
          0.3544999957084656,
          0.0
        ],
        [
          0.5445940494537354,
          0.3527999818325043,
          0.0
        ],
        [
          0.5394940376281738,
          0.36640000343322754,
          0.0
        ],
        [
          0.5394940376281738,
          0.361299991607666,
          0.0
        ],
        [
          0.5394940376281738,
          0.3578999936580658,
          0.0
        ],
        [
          0.5394940376281738,
          0.3561999797821045,
          0.0
        ],
        [
          0.5343940258026123,
          0.36809998750686646,
          0.0
        ],
        [
          0.5343940258026123,
          0.3630000054836273,
          0.0
        ],
        [
          0.5343940258026123,
          0.3596000075340271,
          0.0
        ],
        [
          0.5343940258026123,
          0.3578999936580658,
          0.0
        ]
      ],
      "hand_center": [
        0.544998824596405,
        0.3578190803527832,
        0.0
      ],
      "openness": 2.303232431411743,
      "palm_size": 0.01612764410674572,
      "scale_hint": 0.24,
      "anchors": {
        "forehead": [
          0.5,
          0.23999999463558197,
          0.0
        ],
        "mouth": [
          0.5,
          0.3499999940395355,
          0.0
        ],
        "chin": [
          0.5,
          0.41999998688697815,
          0.0
        ],
        "left_shoulder": [
          0.3799999952316284,
          0.6200000047683716,
          0.0
        ],
        "right_shoulder": [
          0.6200000047683716,
          0.6200000047683716,
          0.0
        ],
        "shoulder_center": [
          0.5,
          0.6200000047683716,
          0.0
        ],
        "nose": [
          0.5,
          0.3100000023841858,
          0.0
        ],
        "scale_hint": 0.24
      }
    },
    {
      "handedness": "right",
      "hand_landmarks": [
        [
          0.5242223143577576,
          0.3799999952316284,
          0.0
        ],
        [
          0.531022310256958,
          0.3782999813556671,
          0.0
        ],
        [
          0.5344223380088806,
          0.3748999834060669,
          0.0
        ],
        [
          0.5378223061561584,
          0.3714999854564667,
          0.0
        ],
        [
          0.54292231798172,
          0.36980000138282776,
          0.0
        ],
        [
          0.5293223261833191,
          0.3630000054836273,
          0.0
        ],
        [
          0.5293223261833191,
          0.3425999879837036,
          0.0
        ],
        [
          0.5293223261833191,
          0.3188000023365021,
          0.0
        ],
        [
          0.5293223261833191,
          0.29159998893737793,
          0.0
        ],
        [
          0.5242223143577576,
          0.36640000343322754,
          0.0
        ],
        [
          0.5242223143577576,
          0.3596000075340271,
          0.0
        ],
        [
          0.5242223143577576,
          0.3544999957084656,
          0.0
        ],
        [
          0.5242223143577576,
          0.3527999818325043,
          0.0
        ],
        [
          0.519122302532196,
          0.36640000343322754,
          0.0
        ],
        [
          0.519122302532196,
          0.361299991607666,
          0.0
        ],
        [
          0.519122302532196,
          0.3578999936580658,
          0.0
        ],
        [
          0.519122302532196,
          0.3561999797821045,
          0.0
        ],
        [
          0.5140222907066345,
          0.36809998750686646,
          0.0
        ],
        [
          0.5140222907066345,
          0.3630000054836273,
          0.0
        ],
        [
          0.5140222907066345,
          0.3596000075340271,
          0.0
        ],
        [
          0.5140222907066345,
          0.3578999936580658,
          0.0
        ]
      ],
      "hand_center": [
        0.5246269702911377,
        0.3578190803527832,
        0.0
      ],
      "openness": 2.303232431411743,
      "palm_size": 0.01612764410674572,
      "scale_hint": 0.24,
      "anchors": {
        "forehead": [
          0.5,
          0.23999999463558197,
          0.0
        ],
        "mouth": [
          0.5,
          0.3499999940395355,
          0.0
        ],
        "chin": [
          0.5,
          0.41999998688697815,
          0.0
        ],
        "left_shoulder": [
          0.3799999952316284,
          0.6200000047683716,
          0.0
        ],
        "right_shoulder": [
          0.6200000047683716,
          0.6200000047683716,
          0.0
        ],
        "shoulder_center": [
          0.5,
          0.6200000047683716,
          0.0
        ],
        "nose": [
          0.5,
          0.3100000023841858,
          0.0
        ],
        "scale_hint": 0.24
      }
    },
    {
      "handedness": "right",
      "hand_landmarks": [
        [
          0.5086155533790588,
          0.3799999952316284,
          0.0
        ],
        [
          0.5154155492782593,
          0.3782999813556671,
          0.0
        ],
        [
          0.5188155770301819,
          0.3748999834060669,
          0.0
        ],
        [
          0.5222155451774597,
          0.3714999854564667,
          0.0
        ],
        [
          0.5273155570030212,
          0.36980000138282776,
          0.0
        ],
        [
          0.5137155652046204,
          0.3630000054836273,
          0.0
        ],
        [
          0.5137155652046204,
          0.3425999879837036,
          0.0
        ],
        [
          0.5137155652046204,
          0.3188000023365021,
          0.0
        ],
        [
          0.5137155652046204,
          0.29159998893737793,
          0.0
        ],
        [
          0.5086155533790588,
          0.36640000343322754,
          0.0
        ],
        [
          0.5086155533790588,
          0.3596000075340271,
          0.0
        ],
        [
          0.5086155533790588,
          0.3544999957084656,
          0.0
        ],
        [
          0.5086155533790588,
          0.3527999818325043,
          0.0
        ],
        [
          0.5035155415534973,
          0.36640000343322754,
          0.0
        ],
        [
          0.5035155415534973,
          0.361299991607666,
          0.0
        ],
        [
          0.5035155415534973,
          0.3578999936580658,
          0.0
        ],
        [
          0.5035155415534973,
          0.3561999797821045,
          0.0
        ],
        [
          0.4984155595302582,
          0.36809998750686646,
          0.0
        ],
        [
          0.4984155595302582,
          0.3630000054836273,
          0.0
        ],
        [
          0.4984155595302582,
          0.3596000075340271,
          0.0
        ],
        [
          0.4984155595302582,
          0.3578999936580658,
          0.0
        ]
      ],
      "hand_center": [
        0.5090203881263733,
        0.3578190803527832,
        0.0
      ],
      "openness": 2.303236246109009,
      "palm_size": 0.01612761616706848,
      "scale_hint": 0.24,
      "anchors": {
        "forehead": [
          0.5,
          0.23999999463558197,
          0.0
        ],
        "mouth": [
          0.5,
          0.3499999940395355,
          0.0
        ],
        "chin": [
          0.5,
          0.41999998688697815,
          0.0
        ],
        "left_shoulder": [
          0.3799999952316284,
          0.6200000047683716,
          0.0
        ],
        "right_shoulder": [
          0.6200000047683716,
          0.6200000047683716,
          0.0
        ],
        "shoulder_center": [
          0.5,
          0.6200000047683716,
          0.0
        ],
        "nose": [
          0.5,
          0.3100000023841858,
          0.0
        ],
        "scale_hint": 0.24
      }
    },
    {
      "handedness": "right",
      "hand_landmarks": [
        [
          0.5006586909294128,
          0.3799999952316284,
          0.0
        ],
        [
          0.5074586868286133,
          0.3782999813556671,
          0.0
        ],
        [
          0.5108587145805359,
          0.3748999834060669,
          0.0
        ],
        [
          0.5142586827278137,
          0.3714999854564667,
          0.0
        ],
        [
          0.5193586945533752,
          0.36980000138282776,
          0.0
        ],
        [
          0.5057587027549744,
          0.3630000054836273,
          0.0
        ],
        [
          0.5057587027549744,
          0.3425999879837036,
          0.0
        ],
        [
          0.5057587027549744,
          0.3188000023365021,
          0.0
        ],
        [
          0.5057587027549744,
          0.29159998893737793,
          0.0
        ],
        [
          0.5006586909294128,
          0.36640000343322754,
          0.0
        ],
        [
          0.5006586909294128,
          0.3596000075340271,
          0.0
        ],
        [
          0.5006586909294128,
          0.3544999957084656,
          0.0
        ],
        [
          0.5006586909294128,
          0.3527999818325043,
          0.0
        ],
        [
          0.4955586791038513,
          0.36640000343322754,
          0.0
        ],
        [
          0.4955586791038513,
          0.361299991607666,
          0.0
        ],
        [
          0.4955586791038513,
          0.3578999936580658,
          0.0
        ],
        [
          0.4955586791038513,
          0.3561999797821045,
          0.0
        ],
        [
          0.4904586970806122,
          0.36809998750686646,
          0.0
        ],
        [
          0.4904586970806122,
          0.3630000054836273,
          0.0
        ],
        [
          0.4904586970806122,
          0.3596000075340271,
          0.0
        ],
        [
          0.4904586970806122,
          0.3578999936580658,
          0.0
        ]
      ],
      "hand_center": [
        0.5010634064674377,
        0.3578190803527832,
        0.0
      ],
      "openness": 2.303236246109009,
      "palm_size": 0.01612761616706848,
      "scale_hint": 0.24,
      "anchors": {
        "forehead": [
          0.5,
          0.23999999463558197,
          0.0
        ],
        "mouth": [
          0.5,
          0.3499999940395355,
          0.0
        ],
        "chin": [
          0.5,
          0.41999998688697815,
          0.0
        ],
        "left_shoulder": [
          0.3799999952316284,
          0.6200000047683716,
          0.0
        ],
        "right_shoulder": [
          0.6200000047683716,
          0.6200000047683716,
          0.0
        ],
        "shoulder_center": [
          0.5,
          0.6200000047683716,
          0.0
        ],
        "nose": [
          0.5,
          0.3100000023841858,
          0.0
        ],
        "scale_hint": 0.24
      }
    },
    {
      "handedness": "right",
      "hand_landmarks": [
        [
          0.5018225312232971,
          0.3799999952316284,
          0.0
        ],
        [
          0.5086225271224976,
          0.3782999813556671,
          0.0
        ],
        [
          0.5120225548744202,
          0.3748999834060669,
          0.0
        ],
        [
          0.515422523021698,
          0.3714999854564667,
          0.0
        ],
        [
          0.5205225348472595,
          0.36980000138282776,
          0.0
        ],
        [
          0.5069225430488586,
          0.3630000054836273,
          0.0
        ],
        [
          0.5069225430488586,
          0.3425999879837036,
          0.0
        ],
        [
          0.5069225430488586,
          0.3188000023365021,
          0.0
        ],
        [
          0.5069225430488586,
          0.29159998893737793,
          0.0
        ],
        [
          0.5018225312232971,
          0.36640000343322754,
          0.0
        ],
        [
          0.5018225312232971,
          0.3596000075340271,
          0.0
        ],
        [
          0.5018225312232971,
          0.3544999957084656,
          0.0
        ],
        [
          0.5018225312232971,
          0.3527999818325043,
          0.0
        ],
        [
          0.4967225193977356,
          0.36640000343322754,
          0.0
        ],
        [
          0.4967225193977356,
          0.361299991607666,
          0.0
        ],
        [
          0.4967225193977356,
          0.3578999936580658,
          0.0
        ],
        [
          0.4967225193977356,
          0.3561999797821045,
          0.0
        ],
        [
          0.49162253737449646,
          0.36809998750686646,
          0.0
        ],
        [
          0.49162253737449646,
          0.3630000054836273,
          0.0
        ],
        [
          0.49162253737449646,
          0.3596000075340271,
          0.0
        ],
        [
          0.49162253737449646,
          0.3578999936580658,
          0.0
        ]
      ],
      "hand_center": [
        0.5022273659706116,
        0.3578190803527832,
        0.0
      ],
      "openness": 2.303236246109009,
      "palm_size": 0.01612761616706848,
      "scale_hint": 0.24,
      "anchors": {
        "forehead": [
          0.5,
          0.23999999463558197,
          0.0
        ],
        "mouth": [
          0.5,
          0.3499999940395355,
          0.0
        ],
        "chin": [
          0.5,
          0.41999998688697815,
          0.0
        ],
        "left_shoulder": [
          0.3799999952316284,
          0.6200000047683716,
          0.0
        ],
        "right_shoulder": [
          0.6200000047683716,
          0.6200000047683716,
          0.0
        ],
        "shoulder_center": [
          0.5,
          0.6200000047683716,
          0.0
        ],
        "nose": [
          0.5,
          0.3100000023841858,
          0.0
        ],
        "scale_hint": 0.24
      }
    },
    {
      "handedness": "right",
      "hand_landmarks": [
        [
          0.5118919610977173,
          0.3799999952316284,
          0.0
        ],
        [
          0.5186919569969177,
          0.3782999813556671,
          0.0
        ],
        [
          0.5220919847488403,
          0.3748999834060669,
          0.0
        ],
        [
          0.5254919528961182,
          0.3714999854564667,
          0.0
        ],
        [
          0.5305919647216797,
          0.36980000138282776,
          0.0
        ],
        [
          0.5169919729232788,
          0.3630000054836273,
          0.0
        ],
        [
          0.5169919729232788,
          0.3425999879837036,
          0.0
        ],
        [
          0.5169919729232788,
          0.3188000023365021,
          0.0
        ],
        [
          0.5169919729232788,
          0.29159998893737793,
          0.0
        ],
        [
          0.5118919610977173,
          0.36640000343322754,
          0.0
        ],
        [
          0.5118919610977173,
          0.3596000075340271,
          0.0
        ],
        [
          0.5118919610977173,
          0.3544999957084656,
          0.0
        ],
        [
          0.5118919610977173,
          0.3527999818325043,
          0.0
        ],
        [
          0.5067919492721558,
          0.36640000343322754,
          0.0
        ],
        [
          0.5067919492721558,
          0.361299991607666,
          0.0
        ],
        [
          0.5067919492721558,
          0.3578999936580658,
          0.0
        ],
        [
          0.5067919492721558,
          0.3561999797821045,
          0.0
        ],
        [
          0.5016919374465942,
          0.36809998750686646,
          0.0
        ],
        [
          0.5016919374465942,
          0.3630000054836273,
          0.0
        ],
        [
          0.5016919374465942,
          0.3596000075340271,
          0.0
        ],
        [
          0.5016919374465942,
          0.3578999936580658,
          0.0
        ]
      ],
      "hand_center": [
        0.512296736240387,
        0.3578190803527832,
        0.0
      ],
      "openness": 2.303232431411743,
      "palm_size": 0.01612764410674572,
      "scale_hint": 0.24,
      "anchors": {
        "forehead": [
          0.5,
          0.23999999463558197,
          0.0
        ],
        "mouth": [
          0.5,
          0.3499999940395355,
          0.0
        ],
        "chin": [
          0.5,
          0.41999998688697815,
          0.0
        ],
        "left_shoulder": [
          0.3799999952316284,
          0.6200000047683716,
          0.0
        ],
        "right_shoulder": [
          0.6200000047683716,
          0.6200000047683716,
          0.0
        ],
        "shoulder_center": [
          0.5,
          0.6200000047683716,
          0.0
        ],
        "nose": [
          0.5,
          0.3100000023841858,
          0.0
        ],
        "scale_hint": 0.24
      }
    },
    {
      "handedness": "right",
      "hand_landmarks": [
        [
          0.5290055871009827,
          0.3799999952316284,
          0.0
        ],
        [
          0.5358055830001831,
          0.3782999813556671,
          0.0
        ],
        [
          0.5392056107521057,
          0.3748999834060669,
          0.0
        ],
        [
          0.5426055788993835,
          0.3714999854564667,
          0.0
        ],
        [
          0.5477055907249451,
          0.36980000138282776,
          0.0
        ],
        [
          0.5341055989265442,
          0.3630000054836273,
          0.0
        ],
        [
          0.5341055989265442,
          0.3425999879837036,
          0.0
        ],
        [
          0.5341055989265442,
          0.3188000023365021,
          0.0
        ],
        [
          0.5341055989265442,
          0.29159998893737793,
          0.0
        ],
        [
          0.5290055871009827,
          0.36640000343322754,
          0.0
        ],
        [
          0.5290055871009827,
          0.3596000075340271,
          0.0
        ],
        [
          0.5290055871009827,
          0.3544999957084656,
          0.0
        ],
        [
          0.5290055871009827,
          0.3527999818325043,
          0.0
        ],
        [
          0.5239055752754211,
          0.36640000343322754,
          0.0
        ],
        [
          0.5239055752754211,
          0.361299991607666,
          0.0
        ],
        [
          0.5239055752754211,
          0.3578999936580658,
          0.0
        ],
        [
          0.5239055752754211,
          0.3561999797821045,
          0.0
        ],
        [
          0.5188055634498596,
          0.36809998750686646,
          0.0
        ],
        [
          0.5188055634498596,
          0.3630000054836273,
          0.0
        ],
        [
          0.5188055634498596,
          0.3596000075340271,
          0.0
        ],
        [
          0.5188055634498596,
          0.3578999936580658,
          0.0
        ]
      ],
      "hand_center": [
        0.5294103622436523,
        0.3578190803527832,
        0.0
      ],
      "openness": 2.303232431411743,
      "palm_size": 0.01612764410674572,
      "scale_hint": 0.24,
      "anchors": {
        "forehead": [
          0.5,
          0.23999999463558197,
          0.0
        ],
        "mouth": [
          0.5,
          0.3499999940395355,
          0.0
        ],
        "chin": [
          0.5,
          0.41999998688697815,
          0.0
        ],
        "left_shoulder": [
          0.3799999952316284,
          0.6200000047683716,
          0.0
        ],
        "right_shoulder": [
          0.6200000047683716,
          0.6200000047683716,
          0.0
        ],
        "shoulder_center": [
          0.5,
          0.6200000047683716,
          0.0
        ],
        "nose": [
          0.5,
          0.3100000023841858,
          0.0
        ],
        "scale_hint": 0.24
      }
    },
    {
      "handedness": "right",
      "hand_landmarks": [
        [
          0.550000011920929,
          0.3799999952316284,
          0.0
        ],
        [
          0.5568000078201294,
          0.3782999813556671,
          0.0
        ],
        [
          0.560200035572052,
          0.3748999834060669,
          0.0
        ],
        [
          0.5636000037193298,
          0.3714999854564667,
          0.0
        ],
        [
          0.5687000155448914,
          0.36980000138282776,
          0.0
        ],
        [
          0.5551000237464905,
          0.3630000054836273,
          0.0
        ],
        [
          0.5551000237464905,
          0.3425999879837036,
          0.0
        ],
        [
          0.5551000237464905,
          0.3188000023365021,
          0.0
        ],
        [
          0.5551000237464905,
          0.29159998893737793,
          0.0
        ],
        [
          0.550000011920929,
          0.36640000343322754,
          0.0
        ],
        [
          0.550000011920929,
          0.3596000075340271,
          0.0
        ],
        [
          0.550000011920929,
          0.3544999957084656,
          0.0
        ],
        [
          0.550000011920929,
          0.3527999818325043,
          0.0
        ],
        [
          0.5449000000953674,
          0.36640000343322754,
          0.0
        ],
        [
          0.5449000000953674,
          0.361299991607666,
          0.0
        ],
        [
          0.5449000000953674,
          0.3578999936580658,
          0.0
        ],
        [
          0.5449000000953674,
          0.3561999797821045,
          0.0
        ],
        [
          0.5397999882698059,
          0.36809998750686646,
          0.0
        ],
        [
          0.5397999882698059,
          0.3630000054836273,
          0.0
        ],
        [
          0.5397999882698059,
          0.3596000075340271,
          0.0
        ],
        [
          0.5397999882698059,
          0.3578999936580658,
          0.0
        ]
      ],
      "hand_center": [
        0.5504047274589539,
        0.3578190803527832,
        0.0
      ],
      "openness": 2.303232431411743,
      "palm_size": 0.01612764410674572,
      "scale_hint": 0.24,
      "anchors": {
        "forehead": [
          0.5,
          0.23999999463558197,
          0.0
        ],
        "mouth": [
          0.5,
          0.3499999940395355,
          0.0
        ],
        "chin": [
          0.5,
          0.41999998688697815,
          0.0
        ],
        "left_shoulder": [
          0.3799999952316284,
          0.6200000047683716,
          0.0
        ],
        "right_shoulder": [
          0.6200000047683716,
          0.6200000047683716,
          0.0
        ],
        "shoulder_center": [
          0.5,
          0.6200000047683716,
          0.0
        ],
        "nose": [
          0.5,
          0.3100000023841858,
          0.0
        ],
        "scale_hint": 0.24
      }
    }
  ]
}